{
  "schema": "jurisdiction-metrics-digest/v1",
  "generated_from": {
    "ranking_index_generated_at": "2026-07-19T04:24:51Z",
    "ranking_index_version": "1.0",
    "builder": "scripts/hna/build_jurisdiction_metrics_digest.mjs",
    "economic_bridge": "scripts/hna/economic_housing_bridge.py"
  },
  "geography": {
    "geoid": "0828830",
    "name": "Fulford (CDP)",
    "type": "cdp",
    "region": "Mountains",
    "containingCounty": "08037"
  },
  "metric_count": 100,
  "min_rate_denominator": 50,
  "metrics": {
    "housing_gap_units": {
      "value": 0,
      "geography_level": "place",
      "confidence": "low",
      "source_id": "ami-gap-place-acs",
      "as_of": "ACS 2020-2024 5-year",
      "measure_type": "level"
    },
    "low_income_households_lte30": {
      "value": 0,
      "geography_level": "place",
      "confidence": "low",
      "source_id": "ami-gap-place-acs",
      "as_of": "ACS 2020-2024 5-year",
      "measure_type": "level"
    },
    "housing_gap_rate_lte30": {
      "value": null,
      "geography_level": "place",
      "confidence": "low",
      "source_id": "ami-gap-place-acs",
      "as_of": "ACS 2020-2024 5-year",
      "measure_type": "level",
      "denominator_key": "low_income_households_lte30",
      "denominator": 0,
      "min_denominator": 50,
      "denominator_floor_applied": true
    },
    "pct_cost_burdened": {
      "value": 0,
      "geography_level": "place",
      "confidence": "low",
      "source_id": "hud-chas-place-apportioned",
      "as_of": "ACS 2020-2024 5-year",
      "measure_type": "level",
      "denominator_key": "renter_households",
      "denominator": 0,
      "min_denominator": 50,
      "denominator_floor_applied": true
    },
    "pct_renter_severe_burdened": {
      "value": 25,
      "geography_level": "place",
      "confidence": "low",
      "source_id": "hud-chas-place-apportioned",
      "as_of": "ACS 2020-2024 5-year",
      "measure_type": "level",
      "denominator_key": "renter_households",
      "denominator": 0,
      "min_denominator": 50,
      "denominator_floor_applied": true
    },
    "pct_deep_tier_burdened": {
      "value": null,
      "geography_level": "place",
      "confidence": "low",
      "source_id": "hud-chas-place-apportioned",
      "as_of": "ACS 2020-2024 5-year",
      "measure_type": "level",
      "denominator_key": "low_income_households_lte30",
      "denominator": 0,
      "min_denominator": 50,
      "denominator_floor_applied": true
    },
    "ami_gap_30pct": {
      "value": 0,
      "geography_level": "place",
      "confidence": "low",
      "source_id": "ami-gap-place-acs",
      "as_of": "ACS 2020-2024 5-year",
      "measure_type": "level"
    },
    "ami_gap_50pct": {
      "value": 0,
      "geography_level": "place",
      "confidence": "low",
      "source_id": "ami-gap-place-acs",
      "as_of": "ACS 2020-2024 5-year",
      "measure_type": "level"
    },
    "ami_gap_60pct": {
      "value": 0,
      "geography_level": "place",
      "confidence": "low",
      "source_id": "ami-gap-place-acs",
      "as_of": "ACS 2020-2024 5-year",
      "measure_type": "level"
    },
    "pct_burdened_lte30": {
      "value": 100,
      "geography_level": "place",
      "confidence": "low",
      "source_id": "hud-chas-place-apportioned",
      "as_of": "ACS 2020-2024 5-year",
      "measure_type": "level",
      "denominator_key": "low_income_households_lte30",
      "denominator": 0,
      "min_denominator": 50,
      "denominator_floor_applied": true
    },
    "pct_burdened_31to50": {
      "value": 100,
      "geography_level": "place",
      "confidence": "low",
      "source_id": "hud-chas-place-apportioned",
      "as_of": "ACS 2020-2024 5-year",
      "measure_type": "level",
      "denominator_key": "low_income_households_lte30",
      "denominator": 0,
      "min_denominator": 50,
      "denominator_floor_applied": true
    },
    "pct_burdened_51to80": {
      "value": 44.4,
      "geography_level": "place",
      "confidence": "low",
      "source_id": "hud-chas-place-apportioned",
      "as_of": "ACS 2020-2024 5-year",
      "measure_type": "level",
      "denominator_key": "low_income_households_lte30",
      "denominator": 0,
      "min_denominator": 50,
      "denominator_floor_applied": true
    },
    "pct_burdened_81to100": {
      "value": 0,
      "geography_level": "place",
      "confidence": "low",
      "source_id": "hud-chas-place-apportioned",
      "as_of": "ACS 2020-2024 5-year",
      "measure_type": "level",
      "denominator_key": "low_income_households_lte30",
      "denominator": 0,
      "min_denominator": 50,
      "denominator_floor_applied": true
    },
    "pct_burdened_100plus": {
      "value": 0,
      "geography_level": "place",
      "confidence": "low",
      "source_id": "hud-chas-place-apportioned",
      "as_of": "ACS 2020-2024 5-year",
      "measure_type": "level",
      "denominator_key": "low_income_households_lte30",
      "denominator": 0,
      "min_denominator": 50,
      "denominator_floor_applied": true
    },
    "pct_owner_burdened_30plus": {
      "value": 25,
      "geography_level": "place",
      "confidence": "low",
      "source_id": "hud-chas-place-apportioned",
      "as_of": "ACS 2020-2024 5-year",
      "measure_type": "level",
      "denominator_key": "owner_households",
      "denominator": 0,
      "min_denominator": 50,
      "denominator_floor_applied": true
    },
    "in_commuters": {
      "value": 4,
      "geography_level": "place",
      "confidence": "low",
      "source_id": "lehd-lodes-place-apportioned",
      "as_of": "LEHD LODES latest committed vintage",
      "measure_type": "level"
    },
    "commute_ratio": {
      "value": 100,
      "geography_level": "place",
      "confidence": "low",
      "source_id": "lehd-lodes-place-apportioned",
      "as_of": "LEHD LODES latest committed vintage",
      "measure_type": "level"
    },
    "population_projection_20yr": {
      "value": 0,
      "geography_level": "county_context",
      "confidence": "low",
      "source_id": "dola-demographic-projections",
      "as_of": "DOLA projection cache",
      "measure_type": "projection"
    },
    "future_units_needed_20yr": {
      "value": null,
      "geography_level": "county_context",
      "confidence": "missing",
      "source_id": "dola-demographic-projections",
      "as_of": "DOLA projection cache",
      "measure_type": "projection"
    },
    "senior_share_growth_pp": {
      "value": 4.83,
      "geography_level": "county_context",
      "confidence": "low",
      "source_id": "dola-demographic-projections",
      "as_of": "DOLA projection cache",
      "measure_type": "level"
    },
    "overcrowding_rate": {
      "value": null,
      "geography_level": "place",
      "confidence": "low",
      "source_id": "acs-profile",
      "as_of": "ACS 2020-2024 5-year",
      "measure_type": "level",
      "denominator_key": "occupied_households",
      "denominator": 0,
      "min_denominator": 50,
      "denominator_floor_applied": true
    },
    "population": {
      "value": 0,
      "geography_level": "place",
      "confidence": "low",
      "source_id": "acs-profile",
      "as_of": "ACS 2020-2024 5-year",
      "measure_type": "level"
    },
    "median_hh_income": {
      "value": 0,
      "geography_level": "place",
      "confidence": "low",
      "source_id": "acs-profile",
      "as_of": "ACS 2020-2024 5-year",
      "measure_type": "level"
    },
    "median_home_value": {
      "value": 0,
      "geography_level": "place",
      "confidence": "missing",
      "source_id": "acs-profile-dp04",
      "as_of": "ACS 2020-2024 5-year",
      "measure_type": "level"
    },
    "home_value_to_income": {
      "value": null,
      "geography_level": "place",
      "confidence": "missing",
      "source_id": "acs-profile-dp04",
      "as_of": "ACS 2020-2024 5-year",
      "measure_type": "level"
    },
    "rent_to_income": {
      "value": null,
      "geography_level": "place",
      "confidence": "missing",
      "source_id": "acs-profile",
      "as_of": "ACS 2020-2024 5-year",
      "measure_type": "level"
    },
    "opportunity_mobility_score": {
      "value": null,
      "geography_level": "place",
      "confidence": "missing",
      "source_id": "opportunity-amenity-context",
      "as_of": "latest committed opportunity context",
      "measure_type": "derived"
    },
    "walkability_score": {
      "value": null,
      "geography_level": "place",
      "confidence": "missing",
      "source_id": "opportunity-amenity-context",
      "as_of": "latest committed opportunity context",
      "measure_type": "derived"
    },
    "amenity_access_score": {
      "value": 2,
      "geography_level": "place",
      "confidence": "low",
      "source_id": "opportunity-amenity-context",
      "as_of": "latest committed opportunity context",
      "measure_type": "derived"
    },
    "qct_dda_score": {
      "value": 100,
      "geography_level": "place",
      "confidence": "low",
      "source_id": "hud-qct-dda",
      "as_of": "latest committed opportunity context",
      "measure_type": "derived"
    },
    "qct_share": {
      "value": 0,
      "geography_level": "place",
      "confidence": "low",
      "source_id": "hud-qct-dda",
      "as_of": "latest committed opportunity context",
      "measure_type": "level"
    },
    "dda_share": {
      "value": 100,
      "geography_level": "place",
      "confidence": "low",
      "source_id": "hud-qct-dda",
      "as_of": "latest committed opportunity context",
      "measure_type": "level"
    },
    "vacancy_rate": {
      "value": 4.6,
      "geography_level": "place",
      "confidence": "low",
      "source_id": "acs-profile",
      "as_of": "ACS 2020-2024 5-year",
      "measure_type": "level",
      "denominator_key": "housing_units",
      "denominator": 32,
      "min_denominator": 50,
      "denominator_floor_applied": true
    },
    "active_market_vacancy_rate": {
      "value": 0,
      "geography_level": "place",
      "confidence": "low",
      "source_id": "acs-profile",
      "as_of": "ACS 2020-2024 5-year",
      "measure_type": "level"
    },
    "raw_rental_vacancy_rate": {
      "value": null,
      "geography_level": "place",
      "confidence": "missing",
      "source_id": "acs-profile",
      "as_of": "ACS 2020-2024 5-year",
      "measure_type": "level"
    },
    "raw_total_vacancy_rate": {
      "value": 50,
      "geography_level": "place",
      "confidence": "low",
      "source_id": "acs-profile",
      "as_of": "ACS 2020-2024 5-year",
      "measure_type": "level"
    },
    "seasonal_vacancy_rate": {
      "value": 50,
      "geography_level": "place",
      "confidence": "low",
      "source_id": "acs-profile",
      "as_of": "ACS 2020-2024 5-year",
      "measure_type": "level"
    },
    "seasonal_share_of_vacant": {
      "value": 100,
      "geography_level": "place",
      "confidence": "low",
      "source_id": "acs-profile",
      "as_of": "ACS 2020-2024 5-year",
      "measure_type": "level"
    },
    "vacancy_renter_base": {
      "value": 0,
      "geography_level": "place",
      "confidence": "low",
      "source_id": "acs-profile",
      "as_of": "ACS 2020-2024 5-year",
      "measure_type": "level"
    },
    "vacancy_adjustment_method": {
      "value": "county_active_market_small_renter_base",
      "geography_level": "place",
      "confidence": "low",
      "source_id": "acs-profile",
      "as_of": "ACS 2020-2024 5-year",
      "measure_type": "level"
    },
    "pct_renters": {
      "value": 0,
      "geography_level": "place",
      "confidence": "low",
      "source_id": "acs-profile",
      "as_of": "ACS 2020-2024 5-year",
      "measure_type": "level",
      "denominator_key": "occupied_households",
      "denominator": 0,
      "min_denominator": 50,
      "denominator_floor_applied": true
    },
    "pct_multifamily": {
      "value": 0,
      "geography_level": "place",
      "confidence": "low",
      "source_id": "acs-profile",
      "as_of": "ACS 2020-2024 5-year",
      "measure_type": "level",
      "denominator_key": "housing_units",
      "denominator": 32,
      "min_denominator": 50,
      "denominator_floor_applied": true
    },
    "pct_sf_detached": {
      "value": 28.1,
      "geography_level": "place",
      "confidence": "low",
      "source_id": "acs-profile",
      "as_of": "ACS 2020-2024 5-year",
      "measure_type": "level",
      "denominator_key": "housing_units",
      "denominator": 32,
      "min_denominator": 50,
      "denominator_floor_applied": true
    },
    "pct_2to4_units": {
      "value": 0,
      "geography_level": "place",
      "confidence": "low",
      "source_id": "acs-profile",
      "as_of": "ACS 2020-2024 5-year",
      "measure_type": "level",
      "denominator_key": "housing_units",
      "denominator": 32,
      "min_denominator": 50,
      "denominator_floor_applied": true
    },
    "gross_rent_median": {
      "value": 0,
      "geography_level": "place",
      "confidence": "low",
      "source_id": "acs-profile",
      "as_of": "ACS 2020-2024 5-year",
      "measure_type": "level"
    },
    "gap_pressure_score": {
      "value": 17.7,
      "geography_level": "place",
      "confidence": "low",
      "source_id": "hna-ranking-index-derived",
      "as_of": "2026-07-19T04:24:51Z",
      "measure_type": "derived"
    },
    "cost_burden_pressure_score": {
      "value": 34.3,
      "geography_level": "place",
      "confidence": "low",
      "source_id": "hud-chas-place-apportioned",
      "as_of": "ACS 2020-2024 5-year",
      "measure_type": "derived"
    },
    "affordability_intensity_score": {
      "value": 0,
      "geography_level": "place",
      "confidence": "low",
      "source_id": "hna-ranking-index-derived",
      "as_of": "2026-07-19T04:24:51Z",
      "measure_type": "derived"
    },
    "future_pressure_score": {
      "value": 67,
      "geography_level": "county_context",
      "confidence": "low",
      "source_id": "dola-demographic-projections",
      "as_of": "DOLA projection cache",
      "measure_type": "derived"
    },
    "overcrowding_score": {
      "value": null,
      "geography_level": "place",
      "confidence": "missing",
      "source_id": "hna-ranking-index-derived",
      "as_of": "2026-07-19T04:24:51Z",
      "measure_type": "derived"
    },
    "commuter_pressure_score": {
      "value": 46.1,
      "geography_level": "place",
      "confidence": "low",
      "source_id": "lehd-lodes-place-apportioned",
      "as_of": "LEHD LODES latest committed vintage",
      "measure_type": "derived"
    },
    "opportunity_score_raw": {
      "value": 36.6,
      "geography_level": "place",
      "confidence": "low",
      "source_id": "opportunity-amenity-context",
      "as_of": "latest committed opportunity context",
      "measure_type": "derived"
    },
    "community_need_core_score": {
      "value": 33.1,
      "geography_level": "place",
      "confidence": "low",
      "source_id": "hna-ranking-index-derived",
      "as_of": "2026-07-19T04:24:51Z",
      "measure_type": "derived"
    },
    "community_need_augmented_raw": {
      "value": 36.1,
      "geography_level": "place",
      "confidence": "low",
      "source_id": "acs-profile",
      "as_of": "ACS 2020-2024 5-year",
      "measure_type": "level"
    },
    "community_need_score": {
      "value": 23,
      "geography_level": "place",
      "confidence": "low",
      "source_id": "hna-ranking-index-derived",
      "as_of": "2026-07-19T04:24:51Z",
      "measure_type": "derived"
    },
    "opportunity_score": {
      "value": 36.6,
      "geography_level": "place",
      "confidence": "low",
      "source_id": "opportunity-amenity-context",
      "as_of": "latest committed opportunity context",
      "measure_type": "derived"
    },
    "overall_need_score_raw": {
      "value": 29.1,
      "geography_level": "place",
      "confidence": "low",
      "source_id": "hna-ranking-index-derived",
      "as_of": "2026-07-19T04:24:51Z",
      "measure_type": "derived"
    },
    "score_confidence_multiplier": {
      "value": 0.85,
      "geography_level": "place",
      "confidence": "low",
      "source_id": "hna-ranking-index-derived",
      "as_of": "2026-07-19T04:24:51Z",
      "measure_type": "derived"
    },
    "overall_need_score": {
      "value": 24.8,
      "geography_level": "place",
      "confidence": "low",
      "source_id": "hna-ranking-index-derived",
      "as_of": "2026-07-19T04:24:51Z",
      "measure_type": "derived"
    },
    "pct_ami_lte30": {
      "value": 16.7,
      "geography_level": "place",
      "confidence": "low",
      "source_id": "hud-chas-place-apportioned",
      "as_of": "ACS 2020-2024 5-year",
      "measure_type": "level",
      "denominator_key": "chas_households_with_ami",
      "denominator": 1.2000000000000002,
      "min_denominator": 50,
      "denominator_floor_applied": true
    },
    "pct_ami_31to50": {
      "value": 16.7,
      "geography_level": "place",
      "confidence": "low",
      "source_id": "hud-chas-place-apportioned",
      "as_of": "ACS 2020-2024 5-year",
      "measure_type": "level",
      "denominator_key": "chas_households_with_ami",
      "denominator": 1.2000000000000002,
      "min_denominator": 50,
      "denominator_floor_applied": true
    },
    "pct_ami_51to80": {
      "value": 25,
      "geography_level": "place",
      "confidence": "low",
      "source_id": "hud-chas-place-apportioned",
      "as_of": "ACS 2020-2024 5-year",
      "measure_type": "level",
      "denominator_key": "chas_households_with_ami",
      "denominator": 1.2000000000000002,
      "min_denominator": 50,
      "denominator_floor_applied": true
    },
    "pct_ami_gt80": {
      "value": 41.7,
      "geography_level": "place",
      "confidence": "low",
      "source_id": "hud-chas-place-apportioned",
      "as_of": "ACS 2020-2024 5-year",
      "measure_type": "level",
      "denominator_key": "chas_households_with_ami",
      "denominator": 1.2000000000000002,
      "min_denominator": 50,
      "denominator_floor_applied": true
    },
    "pct_owner_stock_affordable_80ami": {
      "value": null,
      "geography_level": "place",
      "confidence": "low",
      "source_id": "acs-b25075",
      "as_of": "ACS 2020-2024 5-year",
      "measure_type": "level",
      "denominator_key": "owner_occupied_housing_units",
      "denominator": 0,
      "min_denominator": 50,
      "denominator_floor_applied": true
    },
    "pct_owner_stock_affordable_100ami": {
      "value": null,
      "geography_level": "place",
      "confidence": "low",
      "source_id": "acs-b25075",
      "as_of": "ACS 2020-2024 5-year",
      "measure_type": "level",
      "denominator_key": "owner_occupied_housing_units",
      "denominator": 0,
      "min_denominator": 50,
      "denominator_floor_applied": true
    },
    "pct_owner_stock_affordable_120ami": {
      "value": null,
      "geography_level": "place",
      "confidence": "low",
      "source_id": "acs-b25075",
      "as_of": "ACS 2020-2024 5-year",
      "measure_type": "level",
      "denominator_key": "owner_occupied_housing_units",
      "denominator": 0,
      "min_denominator": 50,
      "denominator_floor_applied": true
    },
    "pct_housing_built_pre1970": {
      "value": 100,
      "geography_level": "place",
      "confidence": "low",
      "source_id": "acs-profile-dp04",
      "as_of": "ACS 2020-2024 5-year",
      "measure_type": "level",
      "denominator_key": "housing_units",
      "denominator": 32,
      "min_denominator": 50,
      "denominator_floor_applied": true
    },
    "pct_no_hs_degree_25plus": {
      "value": null,
      "geography_level": "place",
      "confidence": "low",
      "source_id": "acs-profile-dp02",
      "as_of": "ACS 2020-2024 5-year",
      "measure_type": "level",
      "denominator_key": "population_25plus",
      "denominator": 0,
      "min_denominator": 50,
      "denominator_floor_applied": true
    },
    "pct_single_parent_households": {
      "value": null,
      "geography_level": "place",
      "confidence": "low",
      "source_id": "acs-profile-dp02",
      "as_of": "ACS 2020-2024 5-year",
      "measure_type": "level",
      "denominator_key": "households",
      "denominator": 0,
      "min_denominator": 50,
      "denominator_floor_applied": true
    },
    "pct_age_65_plus": {
      "value": null,
      "geography_level": "place",
      "confidence": "low",
      "source_id": "acs-profile-dp05",
      "as_of": "ACS 2020-2024 5-year",
      "measure_type": "level",
      "denominator_key": "total_population",
      "denominator": 0,
      "min_denominator": 50,
      "denominator_floor_applied": true
    },
    "pct_bipoc_population": {
      "value": null,
      "geography_level": "place",
      "confidence": "low",
      "source_id": "acs-profile-dp05",
      "as_of": "ACS 2020-2024 5-year",
      "measure_type": "level",
      "denominator_key": "total_population",
      "denominator": 0,
      "min_denominator": 50,
      "denominator_floor_applied": true
    },
    "pct_bipoc_households": {
      "value": null,
      "geography_level": "place",
      "confidence": "low",
      "source_id": "acs-b25003",
      "as_of": "ACS 2020-2024 5-year",
      "measure_type": "level",
      "denominator_key": "occupied_housing_units",
      "denominator": 0,
      "min_denominator": 50,
      "denominator_floor_applied": true
    },
    "workforce_housing_pressure_score": {
      "value": 38.6,
      "geography_level": "place",
      "confidence": "high",
      "source_id": "economic-housing-bridge",
      "as_of": "2026-07-19T04:24:51Z",
      "measure_type": "derived",
      "formula_note": "Bounded 0-100 descriptive blend: place home-value pressure (30%), county service-sector share pressure (25%), place commute-ratio pressure (25%), county wage-gap pressure (20%). Not used for ranking."
    },
    "workforce_housing_home_value_pressure": {
      "value": 0,
      "geography_level": "place",
      "confidence": "high",
      "source_id": "economic-housing-bridge",
      "as_of": "2026-07-19T04:24:51Z",
      "measure_type": "derived"
    },
    "workforce_housing_commute_pressure": {
      "value": 66.7,
      "geography_level": "place",
      "confidence": "high",
      "source_id": "economic-housing-bridge",
      "as_of": "2026-07-19T04:24:51Z",
      "measure_type": "derived"
    },
    "workforce_housing_service_sector_pressure": {
      "value": 87.7,
      "geography_level": "county_context",
      "confidence": "high",
      "source_id": "economic-housing-bridge",
      "as_of": "LEHD LODES latest committed vintage",
      "measure_type": "derived"
    },
    "workforce_housing_wage_gap_pressure": {
      "value": 0,
      "geography_level": "county_context",
      "confidence": "high",
      "source_id": "economic-housing-bridge",
      "as_of": "LEHD LODES latest committed vintage",
      "measure_type": "derived"
    },
    "wage_affordability_rent_gap_dollars": {
      "value": -55000,
      "geography_level": "place",
      "confidence": "high",
      "source_id": "economic-housing-bridge",
      "as_of": "2026-07-19T04:24:51Z",
      "measure_type": "level"
    },
    "wage_affordability_ownership_gap_dollars": {
      "value": -55000,
      "geography_level": "place",
      "confidence": "high",
      "source_id": "economic-housing-bridge",
      "as_of": "2026-07-19T04:24:51Z",
      "measure_type": "level"
    },
    "wage_affordability_rent_burden_pct": {
      "value": 0,
      "geography_level": "place",
      "confidence": "high",
      "source_id": "economic-housing-bridge",
      "as_of": "2026-07-19T04:24:51Z",
      "measure_type": "rate"
    },
    "county_service_sector_share_pct": {
      "value": 41.3,
      "geography_level": "county_context",
      "confidence": "high",
      "source_id": "lehd-lodes-county",
      "as_of": "LEHD LODES latest committed vintage",
      "measure_type": "level"
    },
    "county_median_annual_wage_estimate": {
      "value": 55000,
      "geography_level": "county_context",
      "confidence": "medium",
      "source_id": "lehd-lodes-county-earnings-bin-estimate",
      "as_of": "LEHD LODES latest committed vintage",
      "measure_type": "level"
    },
    "county_trend_rent_change_2009_2024_pct": {
      "value": 117.2,
      "geography_level": "county_context",
      "confidence": "high",
      "source_id": "county-housing-cost-trends-acs-cohorts",
      "as_of": "County housing-cost ACS cohorts 2009/2014/2024",
      "measure_type": "trend"
    },
    "county_trend_income_change_2009_2024_pct": {
      "value": 47.1,
      "geography_level": "county_context",
      "confidence": "high",
      "source_id": "county-housing-cost-trends-acs-cohorts",
      "as_of": "County housing-cost ACS cohorts 2009/2014/2024",
      "measure_type": "trend"
    },
    "county_trend_rent_burden_2024_pct": {
      "value": 47.5,
      "geography_level": "county_context",
      "confidence": "high",
      "source_id": "county-housing-cost-trends-acs-cohorts",
      "as_of": "County housing-cost ACS cohorts 2009/2014/2024",
      "measure_type": "level"
    },
    "county_trend_vacancy_rate_2024_pct": {
      "value": 7.5,
      "geography_level": "county_context",
      "confidence": "high",
      "source_id": "county-housing-cost-trends-acs-cohorts",
      "as_of": "County housing-cost ACS cohorts 2009/2014/2024",
      "measure_type": "level"
    },
    "county_trend_total_housing_units_2024": {
      "value": 23520,
      "geography_level": "county_context",
      "confidence": "high",
      "source_id": "county-housing-cost-trends-acs-cohorts",
      "as_of": "County housing-cost ACS cohorts 2009/2014/2024",
      "measure_type": "level"
    },
    "ownership_need_recommendation": {
      "value": "Rental + ownership mix",
      "geography_level": "place",
      "confidence": "medium",
      "source_id": "hna-affordable-ownership-need",
      "as_of": "2026-07-19T04:24:51Z",
      "measure_type": "derived"
    },
    "ownership_need_data_quality": {
      "value": "Medium",
      "geography_level": "place",
      "confidence": "medium",
      "source_id": "hna-affordable-ownership-need",
      "as_of": "2026-07-19T04:24:51Z",
      "measure_type": "level"
    },
    "ownership_need_renter_cost_burdened": {
      "value": 0.3,
      "geography_level": "place",
      "confidence": "medium",
      "source_id": "hna-affordable-ownership-need",
      "as_of": "2026-07-19T04:24:51Z",
      "measure_type": "level"
    },
    "ownership_need_owner_cost_burdened": {
      "value": 0.2,
      "geography_level": "place",
      "confidence": "medium",
      "source_id": "hna-affordable-ownership-need",
      "as_of": "2026-07-19T04:24:51Z",
      "measure_type": "level"
    },
    "ownership_need_severe_renter_cost_burdened": {
      "value": 0.1,
      "geography_level": "place",
      "confidence": "medium",
      "source_id": "hna-affordable-ownership-need",
      "as_of": "2026-07-19T04:24:51Z",
      "measure_type": "level"
    },
    "ownership_need_moderate_income_renter_households": {
      "value": 0.2,
      "geography_level": "place",
      "confidence": "medium",
      "source_id": "hna-affordable-ownership-need",
      "as_of": "2026-07-19T04:24:51Z",
      "measure_type": "level"
    },
    "ownership_need_moderate_income_owner_cost_burdened": {
      "value": 0.1,
      "geography_level": "place",
      "confidence": "medium",
      "source_id": "hna-affordable-ownership-need",
      "as_of": "2026-07-19T04:24:51Z",
      "measure_type": "level"
    },
    "ownership_need_existing_rental_gap_lte80": {
      "value": 0,
      "geography_level": "place",
      "confidence": "medium",
      "source_id": "hna-affordable-ownership-need",
      "as_of": "2026-07-19T04:24:51Z",
      "measure_type": "level"
    },
    "ownership_need_rental_pressure_tier": {
      "value": "Very High",
      "geography_level": "place",
      "confidence": "medium",
      "source_id": "hna-affordable-ownership-need",
      "as_of": "2026-07-19T04:24:51Z",
      "measure_type": "derived"
    },
    "ownership_need_ownership_pressure_tier": {
      "value": "Very High",
      "geography_level": "place",
      "confidence": "medium",
      "source_id": "hna-affordable-ownership-need",
      "as_of": "2026-07-19T04:24:51Z",
      "measure_type": "derived"
    },
    "ownership_need_ownership_fit_tier": {
      "value": "Moderate",
      "geography_level": "place",
      "confidence": "medium",
      "source_id": "hna-affordable-ownership-need",
      "as_of": "2026-07-19T04:24:51Z",
      "measure_type": "derived"
    },
    "ownership_need_affordability_classification": {
      "value": null,
      "geography_level": "place",
      "confidence": "missing",
      "source_id": "hna-affordable-ownership-need",
      "as_of": "2026-07-19T04:24:51Z",
      "measure_type": "level"
    },
    "rank": {
      "value": 458,
      "geography_level": "place",
      "confidence": "high",
      "source_id": "hna-ranking-index-derived",
      "as_of": "2026-07-19T04:24:51Z",
      "measure_type": "derived"
    }
  }
}
