{"type":"FeatureCollection","fetchedAt":"2026-05-31T00:28:58.501Z","features":[{"type":"Feature","geometry":{"type":"Point","coordinates":[-104.815289,39.97895]},"properties":{"PROJECT":"Libretto Apartments","PROJ_ADD":"575 S. 8th Street","PROJ_CTY":"Brighton","PROJ_ST":"CO","CNTY_NAME":"Adams","CNTY_FIPS":"08001","STATEFP":"08","COUNTYFP":"001","N_UNITS":28,"LI_UNITS":28,"YR_PIS":2011,"YR_ALLOC":2011,"CREDIT":"9% Competitive","NON_PROF":null,"QCT":null,"DDA":null,"_source":"CHFA HousingTaxCreditProperties_view","ReportedName":"Libretto Apartments","ComplianceStatus":"Active Compliance","ProjectType":"New Construction","TypeOfCredits":"9% Competitive","UrbanRural":"Urban","Region":"Denver Metro","AwardYear":2011,"ReservationYear":2011,"AwardDate":"2011-01-01","AMIUnits":{"lte20":0,"ami30":6,"ami40":9,"ami50":6,"ami60":7,"ami70":0,"ami80":0,"ami100":0,"ami120":0},"PopulationUnits":{"senior":28,"family":0,"homeless":0,"veteran":0,"supportive":0,"special":0}}},{"type":"Feature","geometry":{"type":"Point","coordinates":[-104.819149,39.885206]},"properties":{"PROJECT":"North Range Crossings","PROJ_ADD":"14350 E 104th Ave.","PROJ_CTY":"Commerce City","PROJ_ST":"CO","CNTY_NAME":"Adams","CNTY_FIPS":"08001","STATEFP":"08","COUNTYFP":"001","N_UNITS":216,"LI_UNITS":216,"YR_PIS":2016,"YR_ALLOC":2016,"CREDIT":"4% Tax Exempt","NON_PROF":null,"QCT":null,"DDA":null,"_source":"CHFA HousingTaxCreditProperties_view","ReportedName":"North Range Crossings","ComplianceStatus":"Active Compliance","ProjectType":"New Construction","TypeOfCredits":"4% Tax Exempt","UrbanRural":"Urban","Region":"Denver Metro","AwardYear":2016,"ReservationYear":2016,"AwardDate":"2016-11-30","AMIUnits":{"lte20":0,"ami30":0,"ami40":0,"ami50":0,"ami60":216,"ami70":0,"ami80":0,"ami100":0,"ami120":0},"PopulationUnits":{"senior":0,"family":216,"homeless":0,"veteran":0,"supportive":0,"special":0}}},{"type":"Feature","geometry":{"type":"Point","coordinates":[-104.940998,39.875281]},"properties":{"PROJECT":"Reserve at Thornton I","PROJ_ADD":"9700 Welby Road","PROJ_CTY":"Thornton","PROJ_ST":"CO","CNTY_NAME":"Adams","CNTY_FIPS":"08001","STATEFP":"08","COUNTYFP":"001","N_UNITS":216,"LI_UNITS":216,"YR_PIS":2003,"YR_ALLOC":2003,"CREDIT":"4% Tax Exempt","NON_PROF":null,"QCT":null,"DDA":null,"_source":"CHFA HousingTaxCreditProperties_view","ReportedName":"Reserve at Thornton I","ComplianceStatus":"Active Compliance","ProjectType":"New Construction","TypeOfCredits":"4% Tax Exempt","UrbanRural":"Urban","Region":"Denver Metro","AwardYear":2003,"ReservationYear":2003,"AwardDate":"2003-01-01","AMIUnits":{"lte20":0,"ami30":0,"ami40":0,"ami50":44,"ami60":172,"ami70":0,"ami80":0,"ami100":0,"ami120":0},"PopulationUnits":{"senior":0,"family":216,"homeless":0,"veteran":0,"supportive":0,"special":0}}},{"type":"Feature","geometry":{"type":"Point","coordinates":[-104.940998,39.875281]},"properties":{"PROJECT":"Reserve at Thornton II","PROJ_ADD":"9700 Welby Road","PROJ_CTY":"Thornton","PROJ_ST":"CO","CNTY_NAME":"Adams","CNTY_FIPS":"08001","STATEFP":"08","COUNTYFP":"001","N_UNITS":60,"LI_UNITS":60,"YR_PIS":2004,"YR_ALLOC":2004,"CREDIT":"9% Competitive","NON_PROF":null,"QCT":null,"DDA":null,"_source":"CHFA HousingTaxCreditProperties_view","ReportedName":"Reserve at Thornton II","ComplianceStatus":"Active Compliance","ProjectType":"New Construction","TypeOfCredits":"9% Competitive","UrbanRural":"Urban","Region":"Denver Metro","AwardYear":2004,"ReservationYear":2004,"AwardDate":"2004-01-01","AMIUnits":{"lte20":0,"ami30":0,"ami40":30,"ami50":30,"ami60":0,"ami70":0,"ami80":0,"ami100":0,"ami120":0},"PopulationUnits":{"senior":0,"family":60,"homeless":0,"veteran":0,"supportive":0,"special":0}}},{"type":"Feature","geometry":{"type":"Point","coordinates":[-105.02544,39.82484]},"properties":{"PROJECT":"Alto Apartments","PROJ_ADD":"7120 Grove Street","PROJ_CTY":"Westminster","PROJ_ST":"CO","CNTY_NAME":"Adams","CNTY_FIPS":"08001","STATEFP":"08","COUNTYFP":"001","N_UNITS":70,"LI_UNITS":70,"YR_PIS":2015,"YR_ALLOC":2015,"CREDIT":"9% Competitive","NON_PROF":null,"QCT":null,"DDA":null,"_source":"CHFA HousingTaxCreditProperties_view","ReportedName":"Alto Apartments","ComplianceStatus":"Active Compliance","ProjectType":"New Construction","TypeOfCredits":"9% Competitive","UrbanRural":"Urban","Region":"Denver Metro","AwardYear":2015,"ReservationYear":2015,"AwardDate":"2015-01-01","AMIUnits":{"lte20":0,"ami30":14,"ami40":0,"ami50":49,"ami60":7,"ami70":0,"ami80":0,"ami100":0,"ami120":0},"PopulationUnits":{"senior":0,"family":70,"homeless":0,"veteran":0,"supportive":0,"special":0}}},{"type":"Feature","geometry":{"type":"Point","coordinates":[-104.917274,39.811784]},"properties":{"PROJECT":"Kearney Plaza","PROJ_ADD":"6140 E 63rd Place","PROJ_CTY":"Commerce City","PROJ_ST":"CO","CNTY_NAME":"Adams","CNTY_FIPS":"08001","STATEFP":"08","COUNTYFP":"001","N_UNITS":50,"LI_UNITS":50,"YR_PIS":2018,"YR_ALLOC":2017,"CREDIT":"4% Tax Exempt","NON_PROF":null,"QCT":null,"DDA":null,"_source":"CHFA HousingTaxCreditProperties_view","ReportedName":"Kearney Plaza","ComplianceStatus":"Active Compliance","ProjectType":"Acquisition/Rehabilitation","TypeOfCredits":"4% Tax Exempt","UrbanRural":"Urban","Region":"Denver Metro","AwardYear":2018,"ReservationYear":2017,"AwardDate":"2018-05-01","AMIUnits":{"lte20":0,"ami30":0,"ami40":0,"ami50":0,"ami60":50,"ami70":0,"ami80":0,"ami100":0,"ami120":0},"PopulationUnits":{"senior":50,"family":0,"homeless":0,"veteran":0,"supportive":0,"special":0}}},{"type":"Feature","geometry":{"type":"Point","coordinates":[-104.99342,39.86146]},"properties":{"PROJECT":"Overlook at Thornton","PROJ_ADD":"647 W. 91st Avenue","PROJ_CTY":"Thornton","PROJ_ST":"CO","CNTY_NAME":"Adams","CNTY_FIPS":"08001","STATEFP":"08","COUNTYFP":"001","N_UNITS":160,"LI_UNITS":160,"YR_PIS":2023,"YR_ALLOC":2022,"CREDIT":"4% Tax Exempt","NON_PROF":null,"QCT":null,"DDA":null,"_source":"CHFA HousingTaxCreditProperties_view","ReportedName":"Overlook at Thornton","ComplianceStatus":"Active Compliance","ProjectType":"Acquisition/Rehabilitation","TypeOfCredits":"4% Tax Exempt","UrbanRural":"Urban","Region":"Denver Metro","AwardYear":2023,"ReservationYear":2022,"AwardDate":"2023-09-26","AMIUnits":{"lte20":0,"ami30":0,"ami40":0,"ami50":0,"ami60":160,"ami70":0,"ami80":0,"ami100":0,"ami120":0},"PopulationUnits":{"senior":0,"family":160,"homeless":0,"veteran":0,"supportive":0,"special":0}}},{"type":"Feature","geometry":{"type":"Point","coordinates":[-104.820187,39.742472]},"properties":{"PROJECT":"Mural Apartments","PROJ_ADD":"16651 E 16th Pl.","PROJ_CTY":"Aurora","PROJ_ST":"CO","CNTY_NAME":"Adams","CNTY_FIPS":"08001","STATEFP":"08","COUNTYFP":"001","N_UNITS":216,"LI_UNITS":216,"YR_PIS":2021,"YR_ALLOC":2021,"CREDIT":"4% Tax Exempt","NON_PROF":null,"QCT":null,"DDA":null,"_source":"CHFA HousingTaxCreditProperties_view","ReportedName":"Mural Apartments","ComplianceStatus":"Active Compliance","ProjectType":"New Construction","TypeOfCredits":"4% Tax Exempt","UrbanRural":"Urban","Region":"Denver Metro","AwardYear":2021,"ReservationYear":2021,"AwardDate":"2021-08-10","AMIUnits":{"lte20":0,"ami30":30,"ami40":48,"ami50":0,"ami60":0,"ami70":138,"ami80":0,"ami100":0,"ami120":0},"PopulationUnits":{"senior":0,"family":216,"homeless":0,"veteran":0,"supportive":0,"special":0}}},{"type":"Feature","geometry":{"type":"Point","coordinates":[-104.82849,39.91384]},"properties":{"PROJECT":"Retreat at Brighton Ridge Apartment Homes","PROJ_ADD":"South and West of 120th and Potomac","PROJ_CTY":"Brighton","PROJ_ST":"CO","CNTY_NAME":"Adams","CNTY_FIPS":"08001","STATEFP":"08","COUNTYFP":"001","N_UNITS":264,"LI_UNITS":264,"YR_PIS":2023,"YR_ALLOC":2022,"CREDIT":"4% Tax Exempt","NON_PROF":null,"QCT":null,"DDA":null,"_source":"CHFA HousingTaxCreditProperties_view","ReportedName":"Retreat at Brighton Ridge Apartment Homes","ComplianceStatus":"Active Compliance","ProjectType":"New Construction","TypeOfCredits":"4% Tax Exempt","UrbanRural":"Urban","Region":"Denver Metro","AwardYear":2023,"ReservationYear":2022,"AwardDate":"2023-04-25","AMIUnits":{"lte20":0,"ami30":0,"ami40":0,"ami50":0,"ami60":264,"ami70":0,"ami80":0,"ami100":0,"ami120":0},"PopulationUnits":{"senior":0,"family":264,"homeless":0,"veteran":0,"supportive":0,"special":0}}},{"type":"Feature","geometry":{"type":"Point","coordinates":[-104.981101,39.899349]},"properties":{"PROJECT":"Squire Village","PROJ_ADD":"11180 Grant Drive","PROJ_CTY":"Northglenn","PROJ_ST":"CO","CNTY_NAME":"Adams","CNTY_FIPS":"08001","STATEFP":"08","COUNTYFP":"001","N_UNITS":51,"LI_UNITS":50,"YR_PIS":2003,"YR_ALLOC":2003,"CREDIT":"4% Tax Exempt","NON_PROF":null,"QCT":null,"DDA":null,"_source":"CHFA HousingTaxCreditProperties_view","ReportedName":"Squire Village","ComplianceStatus":"Active Compliance","ProjectType":"Acquisition/Rehabilitation","TypeOfCredits":"4% Tax Exempt","UrbanRural":"Urban","Region":"Denver Metro","AwardYear":2003,"ReservationYear":2003,"AwardDate":"2003-01-01","AMIUnits":{"lte20":0,"ami30":0,"ami40":0,"ami50":0,"ami60":50,"ami70":0,"ami80":0,"ami100":1,"ami120":0},"PopulationUnits":{"senior":0,"family":51,"homeless":0,"veteran":0,"supportive":0,"special":0}}},{"type":"Feature","geometry":{"type":"Point","coordinates":[-104.79813,39.98497]},"properties":{"PROJECT":"Spring Hollow","PROJ_ADD":"141 S. 20th Ave.","PROJ_CTY":"Brighton","PROJ_ST":"CO","CNTY_NAME":"Adams","CNTY_FIPS":"08001","STATEFP":"08","COUNTYFP":"001","N_UNITS":108,"LI_UNITS":108,"YR_PIS":2001,"YR_ALLOC":2001,"CREDIT":"4% Tax Exempt","NON_PROF":null,"QCT":null,"DDA":null,"_source":"CHFA HousingTaxCreditProperties_view","ReportedName":"Spring Hollow","ComplianceStatus":"Active Compliance","ProjectType":"New Construction","TypeOfCredits":"4% Tax Exempt","UrbanRural":"Urban","Region":"Denver Metro","AwardYear":2001,"ReservationYear":2001,"AwardDate":"2001-01-01","AMIUnits":{"lte20":0,"ami30":0,"ami40":0,"ami50":0,"ami60":108,"ami70":0,"ami80":0,"ami100":0,"ami120":0},"PopulationUnits":{"senior":0,"family":108,"homeless":0,"veteran":0,"supportive":0,"special":0}}},{"type":"Feature","geometry":{"type":"Point","coordinates":[-105.041036,39.833562]},"properties":{"PROJECT":"Bradburn Gardens","PROJ_ADD":"7545 Bradburn Blvd","PROJ_CTY":"Westminster","PROJ_ST":"CO","CNTY_NAME":"Adams","CNTY_FIPS":"08001","STATEFP":"08","COUNTYFP":"001","N_UNITS":44,"LI_UNITS":44,"YR_PIS":2000,"YR_ALLOC":2000,"CREDIT":"4% Tax Exempt","NON_PROF":null,"QCT":null,"DDA":null,"_source":"CHFA HousingTaxCreditProperties_view","ReportedName":"Bradburn Gardens","ComplianceStatus":"Active Compliance","ProjectType":"Rehabilitation Only","TypeOfCredits":"4% Tax Exempt","UrbanRural":"Urban","Region":"Denver Metro","AwardYear":2000,"ReservationYear":2000,"AwardDate":"2000-01-01","AMIUnits":{"lte20":0,"ami30":0,"ami40":0,"ami50":0,"ami60":44,"ami70":0,"ami80":0,"ami100":0,"ami120":0},"PopulationUnits":{"senior":0,"family":44,"homeless":0,"veteran":0,"supportive":0,"special":0}}},{"type":"Feature","geometry":{"type":"Point","coordinates":[-104.990967,39.90259]},"properties":{"PROJECT":"Greens of Northglenn","PROJ_ADD":"350 W. 114 Ave.","PROJ_CTY":"Northglenn","PROJ_ST":"CO","CNTY_NAME":"Adams","CNTY_FIPS":"08001","STATEFP":"08","COUNTYFP":"001","N_UNITS":128,"LI_UNITS":127,"YR_PIS":1996,"YR_ALLOC":1996,"CREDIT":"9% Competitive","NON_PROF":null,"QCT":null,"DDA":null,"_source":"CHFA HousingTaxCreditProperties_view","ReportedName":"Greens of Northglenn","ComplianceStatus":"Active Compliance","ProjectType":"New Construction","TypeOfCredits":"9% Competitive","UrbanRural":"Urban","Region":"Denver Metro","AwardYear":1996,"ReservationYear":1996,"AwardDate":"1996-01-01","AMIUnits":{"lte20":0,"ami30":0,"ami40":89,"ami50":38,"ami60":0,"ami70":0,"ami80":0,"ami100":1,"ami120":0},"PopulationUnits":{"senior":0,"family":128,"homeless":0,"veteran":0,"supportive":0,"special":0}}},{"type":"Feature","geometry":{"type":"Point","coordinates":[-104.83159,39.97535]},"properties":{"PROJECT":"Pinecone Village","PROJ_ADD":"707-751 Miller Ave.","PROJ_CTY":"Brighton","PROJ_ST":"CO","CNTY_NAME":"Adams","CNTY_FIPS":"08001","STATEFP":"08","COUNTYFP":"001","N_UNITS":40,"LI_UNITS":40,"YR_PIS":1991,"YR_ALLOC":1991,"CREDIT":"9% Competitive","NON_PROF":null,"QCT":null,"DDA":null,"_source":"CHFA HousingTaxCreditProperties_view","ReportedName":"Pinecone Village","ComplianceStatus":"Active Compliance","ProjectType":"New Construction","TypeOfCredits":"9% Competitive","UrbanRural":"Urban","Region":"Denver Metro","AwardYear":1991,"ReservationYear":1991,"AwardDate":"1991-01-01","AMIUnits":{"lte20":0,"ami30":0,"ami40":0,"ami50":23,"ami60":17,"ami70":0,"ami80":0,"ami100":0,"ami120":0},"PopulationUnits":{"senior":0,"family":40,"homeless":0,"veteran":0,"supportive":0,"special":0}}},{"type":"Feature","geometry":{"type":"Point","coordinates":[-105.021347,39.854896]},"properties":{"PROJECT":"Overlook at Uplands","PROJ_ADD":"8775 Clay Street","PROJ_CTY":"Westminster","PROJ_ST":"CO","CNTY_NAME":"Adams","CNTY_FIPS":"08001","STATEFP":"08","COUNTYFP":"001","N_UNITS":247,"LI_UNITS":247,"YR_PIS":2023,"YR_ALLOC":2023,"CREDIT":"4% Tax Exempt","NON_PROF":null,"QCT":null,"DDA":null,"_source":"CHFA HousingTaxCreditProperties_view","ReportedName":"Overlook at Uplands","ComplianceStatus":"Active Compliance","ProjectType":"New Construction","TypeOfCredits":"4% Tax Exempt","UrbanRural":"Urban","Region":"Denver Metro","AwardYear":2023,"ReservationYear":2023,"AwardDate":"2023-10-17","AMIUnits":{"lte20":0,"ami30":0,"ami40":13,"ami50":40,"ami60":129,"ami70":65,"ami80":0,"ami100":0,"ami120":0},"PopulationUnits":{"senior":0,"family":247,"homeless":0,"veteran":0,"supportive":0,"special":0}}},{"type":"Feature","geometry":{"type":"Point","coordinates":[-104.90725,39.799332]},"properties":{"PROJECT":"Pinecrest at Commerce City","PROJ_ADD":"5659 Olive Street","PROJ_CTY":"Commerce City","PROJ_ST":"CO","CNTY_NAME":"Adams","CNTY_FIPS":"08001","STATEFP":"08","COUNTYFP":"001","N_UNITS":112,"LI_UNITS":111,"YR_PIS":2004,"YR_ALLOC":2004,"CREDIT":"9% Competitive","NON_PROF":null,"QCT":null,"DDA":null,"_source":"CHFA HousingTaxCreditProperties_view","ReportedName":"Pinecrest at Commerce City","ComplianceStatus":"Active Compliance","ProjectType":"Rehabilitation Only","TypeOfCredits":"9% Competitive","UrbanRural":"Urban","Region":"Denver Metro","AwardYear":2004,"ReservationYear":2004,"AwardDate":"2004-01-01","AMIUnits":{"lte20":0,"ami30":0,"ami40":23,"ami50":68,"ami60":20,"ami70":0,"ami80":0,"ami100":1,"ami120":0},"PopulationUnits":{"senior":0,"family":112,"homeless":0,"veteran":0,"supportive":0,"special":0}}},{"type":"Feature","geometry":{"type":"Point","coordinates":[-104.940793,39.824896]},"properties":{"PROJECT":"Junction 72","PROJ_ADD":"7001 Colorado Blvd","PROJ_CTY":"Commerce City","PROJ_ST":"CO","CNTY_NAME":"Adams","CNTY_FIPS":"08001","STATEFP":"08","COUNTYFP":"001","N_UNITS":93,"LI_UNITS":93,"YR_PIS":2023,"YR_ALLOC":2022,"CREDIT":"4% Tax Exempt","NON_PROF":null,"QCT":null,"DDA":null,"_source":"CHFA HousingTaxCreditProperties_view","ReportedName":"Junction 72","ComplianceStatus":"Active Compliance","ProjectType":"New Construction","TypeOfCredits":"4% Tax Exempt","UrbanRural":"Urban","Region":"Denver Metro","AwardYear":2023,"ReservationYear":2022,"AwardDate":"2023-01-24","AMIUnits":{"lte20":0,"ami30":5,"ami40":0,"ami50":0,"ami60":88,"ami70":0,"ami80":0,"ami100":0,"ami120":0},"PopulationUnits":{"senior":0,"family":93,"homeless":0,"veteran":0,"supportive":0,"special":0}}},{"type":"Feature","geometry":{"type":"Point","coordinates":[-104.847906,39.744126]},"properties":{"PROJECT":"Paris Family Housing","PROJ_ADD":"1702 Paris Street","PROJ_CTY":"Aurora","PROJ_ST":"CO","CNTY_NAME":"Adams","CNTY_FIPS":"08001","STATEFP":"08","COUNTYFP":"001","N_UNITS":39,"LI_UNITS":39,"YR_PIS":2016,"YR_ALLOC":2016,"CREDIT":"9% Competitive","NON_PROF":null,"QCT":null,"DDA":null,"_source":"CHFA HousingTaxCreditProperties_view","ReportedName":"Paris Family Housing","ComplianceStatus":"Active Compliance","ProjectType":"New Construction","TypeOfCredits":"9% Competitive","UrbanRural":"Urban","Region":"Denver Metro","AwardYear":2016,"ReservationYear":2016,"AwardDate":"2016-09-01","AMIUnits":{"lte20":0,"ami30":9,"ami40":11,"ami50":19,"ami60":0,"ami70":0,"ami80":0,"ami100":0,"ami120":0},"PopulationUnits":{"senior":0,"family":39,"homeless":0,"veteran":0,"supportive":0,"special":0}}},{"type":"Feature","geometry":{"type":"Point","coordinates":[-104.92605,39.80944]},"properties":{"PROJECT":"Landing","PROJ_ADD":"6230 Glencoe St.","PROJ_CTY":"Commerce City","PROJ_ST":"CO","CNTY_NAME":"Adams","CNTY_FIPS":"08001","STATEFP":"08","COUNTYFP":"001","N_UNITS":223,"LI_UNITS":223,"YR_PIS":2019,"YR_ALLOC":2019,"CREDIT":"4% Tax Exempt","NON_PROF":null,"QCT":null,"DDA":null,"_source":"CHFA HousingTaxCreditProperties_view","ReportedName":"Landing","ComplianceStatus":"Active Compliance","ProjectType":"New Construction","TypeOfCredits":"4% Tax Exempt","UrbanRural":"Urban","Region":"Denver Metro","AwardYear":2019,"ReservationYear":2019,"AwardDate":"2019-12-17","AMIUnits":{"lte20":0,"ami30":12,"ami40":0,"ami50":0,"ami60":211,"ami70":0,"ami80":0,"ami100":0,"ami120":0},"PopulationUnits":{"senior":0,"family":223,"homeless":0,"veteran":0,"supportive":0,"special":0}}},{"type":"Feature","geometry":{"type":"Point","coordinates":[-104.916022,39.810196]},"properties":{"PROJECT":"Village Crest Apartments","PROJ_ADD":"6201 E. 62nd Avenue","PROJ_CTY":"Commerce City","PROJ_ST":"CO","CNTY_NAME":"Adams","CNTY_FIPS":"08001","STATEFP":"08","COUNTYFP":"001","N_UNITS":120,"LI_UNITS":120,"YR_PIS":2018,"YR_ALLOC":2017,"CREDIT":"4% Tax Exempt","NON_PROF":null,"QCT":null,"DDA":null,"_source":"CHFA HousingTaxCreditProperties_view","ReportedName":"Village Crest Apartments","ComplianceStatus":"Active Compliance","ProjectType":"Acquisition/Rehabilitation","TypeOfCredits":"4% Tax Exempt","UrbanRural":"Urban","Region":"Denver Metro","AwardYear":2018,"ReservationYear":2017,"AwardDate":"2018-01-16","AMIUnits":{"lte20":0,"ami30":0,"ami40":0,"ami50":0,"ami60":120,"ami70":0,"ami80":0,"ami100":0,"ami120":0},"PopulationUnits":{"senior":0,"family":120,"homeless":0,"veteran":0,"supportive":0,"special":0}}},{"type":"Feature","geometry":{"type":"Point","coordinates":[-105.019722,39.847711]},"properties":{"PROJECT":"Village at Homewood Point","PROJ_ADD":"8310 Clay Street","PROJ_CTY":"Westminster","PROJ_ST":"CO","CNTY_NAME":"Adams","CNTY_FIPS":"08001","STATEFP":"08","COUNTYFP":"001","N_UNITS":72,"LI_UNITS":72,"YR_PIS":2008,"YR_ALLOC":2008,"CREDIT":"9% Competitive","NON_PROF":null,"QCT":null,"DDA":null,"_source":"CHFA HousingTaxCreditProperties_view","ReportedName":"Village at Homewood Point","ComplianceStatus":"Active Compliance","ProjectType":"New Construction","TypeOfCredits":"9% Competitive","UrbanRural":"Urban","Region":"Denver Metro","AwardYear":2008,"ReservationYear":2008,"AwardDate":"2008-01-01","AMIUnits":{"lte20":0,"ami30":0,"ami40":33,"ami50":39,"ami60":0,"ami70":0,"ami80":0,"ami100":0,"ami120":0},"PopulationUnits":{"senior":72,"family":0,"homeless":0,"veteran":0,"supportive":0,"special":0}}},{"type":"Feature","geometry":{"type":"Point","coordinates":[-105.005479,39.842055]},"properties":{"PROJECT":"Elmwood North","PROJ_ADD":"8000 N. Pecos St.","PROJ_CTY":"Denver","PROJ_ST":"CO","CNTY_NAME":"Adams","CNTY_FIPS":"08001","STATEFP":"08","COUNTYFP":"001","N_UNITS":70,"LI_UNITS":0,"YR_PIS":2025,"YR_ALLOC":2025,"CREDIT":"MIHTC","NON_PROF":null,"QCT":null,"DDA":null,"_source":"CHFA HousingTaxCreditProperties_view","ReportedName":"Elmwood North","ComplianceStatus":"Active Compliance","ProjectType":"New Construction","TypeOfCredits":"MIHTC","UrbanRural":"Urban","Region":"Denver Metro","AwardYear":2025,"ReservationYear":2025,"AwardDate":"2025-07-18","AMIUnits":{"lte20":0,"ami30":0,"ami40":0,"ami50":0,"ami60":0,"ami70":0,"ami80":35,"ami100":0,"ami120":0},"PopulationUnits":{"senior":0,"family":70,"homeless":0,"veteran":0,"supportive":0,"special":0}}},{"type":"Feature","geometry":{"type":"Point","coordinates":[-104.84644,39.75996]},"properties":{"PROJECT":"Peoria Crossing I","PROJ_ADD":"3002 N Peoria St.","PROJ_CTY":"Aurora","PROJ_ST":"CO","CNTY_NAME":"Adams","CNTY_FIPS":"08001","STATEFP":"08","COUNTYFP":"001","N_UNITS":82,"LI_UNITS":82,"YR_PIS":2017,"YR_ALLOC":2017,"CREDIT":"4% and State","NON_PROF":null,"QCT":null,"DDA":null,"_source":"CHFA HousingTaxCreditProperties_view","ReportedName":"Peoria Crossing I","ComplianceStatus":"Active Compliance","ProjectType":"New Construction","TypeOfCredits":"4% and State","UrbanRural":"Urban","Region":"Denver Metro","AwardYear":2017,"ReservationYear":2017,"AwardDate":"2017-04-17","AMIUnits":{"lte20":0,"ami30":8,"ami40":16,"ami50":0,"ami60":58,"ami70":0,"ami80":0,"ami100":0,"ami120":0},"PopulationUnits":{"senior":0,"family":73,"homeless":0,"veteran":9,"supportive":0,"special":0}}},{"type":"Feature","geometry":{"type":"Point","coordinates":[-105.003155,39.85656]},"properties":{"PROJECT":"Orchard Hill Senior Apartments","PROJ_ADD":"1353 West 88th Avenue","PROJ_CTY":"Thornton","PROJ_ST":"CO","CNTY_NAME":"Adams","CNTY_FIPS":"08001","STATEFP":"08","COUNTYFP":"001","N_UNITS":88,"LI_UNITS":88,"YR_PIS":2000,"YR_ALLOC":2000,"CREDIT":"9% Competitive","NON_PROF":null,"QCT":null,"DDA":null,"_source":"CHFA HousingTaxCreditProperties_view","ReportedName":"Orchard Hill Senior Apartments","ComplianceStatus":"Active Compliance","ProjectType":"New Construction","TypeOfCredits":"9% Competitive","UrbanRural":"Urban","Region":"Denver Metro","AwardYear":2000,"ReservationYear":2000,"AwardDate":"2000-01-01","AMIUnits":{"lte20":0,"ami30":0,"ami40":47,"ami50":40,"ami60":0,"ami70":0,"ami80":0,"ami100":0,"ami120":0},"PopulationUnits":{"senior":88,"family":0,"homeless":0,"veteran":0,"supportive":0,"special":0}}},{"type":"Feature","geometry":{"type":"Point","coordinates":[-104.96726,39.91556]},"properties":{"PROJECT":"Karl's Farm Apartments","PROJ_ADD":"1601 E 121st Ave","PROJ_CTY":"Northglenn","PROJ_ST":"CO","CNTY_NAME":"Adams","CNTY_FIPS":"08001","STATEFP":"08","COUNTYFP":"001","N_UNITS":164,"LI_UNITS":162,"YR_PIS":2021,"YR_ALLOC":2021,"CREDIT":"4% Tax Exempt","NON_PROF":null,"QCT":null,"DDA":null,"_source":"CHFA HousingTaxCreditProperties_view","ReportedName":"Karl's Farm Apartments","ComplianceStatus":"Active Compliance","ProjectType":"New Construction","TypeOfCredits":"4% Tax Exempt","UrbanRural":"Urban","Region":"Denver Metro","AwardYear":2021,"ReservationYear":2021,"AwardDate":"2021-05-25","AMIUnits":{"lte20":0,"ami30":0,"ami40":0,"ami50":0,"ami60":162,"ami70":0,"ami80":0,"ami100":0,"ami120":0},"PopulationUnits":{"senior":164,"family":0,"homeless":0,"veteran":0,"supportive":0,"special":0}}},{"type":"Feature","geometry":{"type":"Point","coordinates":[-105.02797,39.87368]},"properties":{"PROJECT":"St Mark Village","PROJ_ADD":"3101 W 97th Ave","PROJ_CTY":"Westminster","PROJ_ST":"CO","CNTY_NAME":"Adams","CNTY_FIPS":"08001","STATEFP":"08","COUNTYFP":"001","N_UNITS":216,"LI_UNITS":215,"YR_PIS":2018,"YR_ALLOC":2017,"CREDIT":"4% Tax Exempt","NON_PROF":null,"QCT":null,"DDA":null,"_source":"CHFA HousingTaxCreditProperties_view","ReportedName":"St Mark Village","ComplianceStatus":"Active Compliance","ProjectType":"New Construction","TypeOfCredits":"4% Tax Exempt","UrbanRural":"Urban","Region":"Denver Metro","AwardYear":2018,"ReservationYear":2017,"AwardDate":"2018-04-24","AMIUnits":{"lte20":0,"ami30":0,"ami40":0,"ami50":0,"ami60":215,"ami70":0,"ami80":0,"ami100":0,"ami120":0},"PopulationUnits":{"senior":0,"family":216,"homeless":0,"veteran":0,"supportive":0,"special":0}}},{"type":"Feature","geometry":{"type":"Point","coordinates":[-104.834223,39.975534]},"properties":{"PROJECT":"Riverwalk Apartments","PROJ_ADD":"744 Mockingbird St., Suite A-100","PROJ_CTY":"Brighton","PROJ_ST":"CO","CNTY_NAME":"Adams","CNTY_FIPS":"08001","STATEFP":"08","COUNTYFP":"001","N_UNITS":132,"LI_UNITS":87,"YR_PIS":1998,"YR_ALLOC":1998,"CREDIT":"4% Tax Exempt","NON_PROF":null,"QCT":null,"DDA":null,"_source":"CHFA HousingTaxCreditProperties_view","ReportedName":"Riverwalk Apartments","ComplianceStatus":"Active Compliance","ProjectType":"New Construction","TypeOfCredits":"4% Tax Exempt","UrbanRural":"Urban","Region":"Denver Metro","AwardYear":1998,"ReservationYear":1998,"AwardDate":"1998-01-01","AMIUnits":{"lte20":0,"ami30":0,"ami40":0,"ami50":10,"ami60":77,"ami70":0,"ami80":0,"ami100":45,"ami120":0},"PopulationUnits":{"senior":0,"family":132,"homeless":0,"veteran":0,"supportive":0,"special":0}}},{"type":"Feature","geometry":{"type":"Point","coordinates":[-104.92433,39.81007]},"properties":{"PROJECT":"Greyhound Park Empowerment Apartments","PROJ_ADD":"5424 E 62nd Place","PROJ_CTY":"Commerce City","PROJ_ST":"CO","CNTY_NAME":"Adams","CNTY_FIPS":"08001","STATEFP":"08","COUNTYFP":"001","N_UNITS":50,"LI_UNITS":50,"YR_PIS":2021,"YR_ALLOC":2021,"CREDIT":"9% Competitive","NON_PROF":null,"QCT":null,"DDA":null,"_source":"CHFA HousingTaxCreditProperties_view","ReportedName":"Greyhound Park Empowerment Apartments","ComplianceStatus":"Active Compliance","ProjectType":"New Construction","TypeOfCredits":"9% Competitive","UrbanRural":"Urban","Region":"Denver Metro","AwardYear":2021,"ReservationYear":2021,"AwardDate":"2021-05-04","AMIUnits":{"lte20":0,"ami30":50,"ami40":0,"ami50":0,"ami60":0,"ami70":0,"ami80":0,"ami100":0,"ami120":0},"PopulationUnits":{"senior":0,"family":0,"homeless":0,"veteran":0,"supportive":50,"special":0}}},{"type":"Feature","geometry":{"type":"Point","coordinates":[-104.815251,39.743334]},"properties":{"PROJECT":"Los Altos","PROJ_ADD":"1671 Altura Boulevard","PROJ_CTY":"Aurora","PROJ_ST":"CO","CNTY_NAME":"Adams","CNTY_FIPS":"08001","STATEFP":"08","COUNTYFP":"001","N_UNITS":137,"LI_UNITS":137,"YR_PIS":2022,"YR_ALLOC":2022,"CREDIT":"4% and State","NON_PROF":null,"QCT":null,"DDA":null,"_source":"CHFA HousingTaxCreditProperties_view","ReportedName":"Los Altos","ComplianceStatus":"Active Compliance","ProjectType":"New Construction","TypeOfCredits":"4% and State","UrbanRural":"Urban","Region":"Denver Metro","AwardYear":2022,"ReservationYear":2022,"AwardDate":"2022-11-08","AMIUnits":{"lte20":0,"ami30":7,"ami40":7,"ami50":34,"ami60":55,"ami70":34,"ami80":0,"ami100":0,"ami120":0},"PopulationUnits":{"senior":0,"family":137,"homeless":0,"veteran":0,"supportive":0,"special":0}}},{"type":"Feature","geometry":{"type":"Point","coordinates":[-104.84566,39.7468]},"properties":{"PROJECT":"Liberty View","PROJ_ADD":"1959 Quentin Street","PROJ_CTY":"Aurora","PROJ_ST":"CO","CNTY_NAME":"Adams","CNTY_FIPS":"08001","STATEFP":"08","COUNTYFP":"001","N_UNITS":59,"LI_UNITS":59,"YR_PIS":2020,"YR_ALLOC":2020,"CREDIT":"4% and State","NON_PROF":null,"QCT":null,"DDA":null,"_source":"CHFA HousingTaxCreditProperties_view","ReportedName":"Liberty View","ComplianceStatus":"Active Compliance","ProjectType":"New Construction","TypeOfCredits":"4% and State","UrbanRural":"Urban","Region":"Denver Metro","AwardYear":2020,"ReservationYear":2020,"AwardDate":"2020-12-31","AMIUnits":{"lte20":0,"ami30":16,"ami40":7,"ami50":13,"ami60":23,"ami70":0,"ami80":0,"ami100":0,"ami120":0},"PopulationUnits":{"senior":0,"family":0,"homeless":0,"veteran":59,"supportive":0,"special":0}}},{"type":"Feature","geometry":{"type":"Point","coordinates":[-104.81387,39.978203]},"properties":{"PROJECT":"Libretto Apartments Phase II","PROJ_ADD":"577 South 8th Ave.","PROJ_CTY":"Brighton","PROJ_ST":"CO","CNTY_NAME":"Adams","CNTY_FIPS":"08001","STATEFP":"08","COUNTYFP":"001","N_UNITS":42,"LI_UNITS":42,"YR_PIS":2018,"YR_ALLOC":2018,"CREDIT":"9% Competitive","NON_PROF":null,"QCT":null,"DDA":null,"_source":"CHFA HousingTaxCreditProperties_view","ReportedName":"Libretto Apartments Phase II","ComplianceStatus":"Active Compliance","ProjectType":"New Construction","TypeOfCredits":"9% Competitive","UrbanRural":"Urban","Region":"Denver Metro","AwardYear":2018,"ReservationYear":2018,"AwardDate":"2018-09-14","AMIUnits":{"lte20":0,"ami30":5,"ami40":12,"ami50":17,"ami60":8,"ami70":0,"ami80":0,"ami100":0,"ami120":0},"PopulationUnits":{"senior":42,"family":0,"homeless":0,"veteran":0,"supportive":0,"special":0}}},{"type":"Feature","geometry":{"type":"Point","coordinates":[-105.02799,39.83395]},"properties":{"PROJECT":"Westminster Commons","PROJ_ADD":"3180 W. 76th Ave.","PROJ_CTY":"Westminster","PROJ_ST":"CO","CNTY_NAME":"Adams","CNTY_FIPS":"08001","STATEFP":"08","COUNTYFP":"001","N_UNITS":130,"LI_UNITS":130,"YR_PIS":2012,"YR_ALLOC":2012,"CREDIT":"4% Tax Exempt","NON_PROF":null,"QCT":null,"DDA":null,"_source":"CHFA HousingTaxCreditProperties_view","ReportedName":"Westminster Commons","ComplianceStatus":"Active Compliance","ProjectType":"Acquisition/Rehabilitation","TypeOfCredits":"4% Tax Exempt","UrbanRural":"Urban","Region":"Denver Metro","AwardYear":2012,"ReservationYear":2012,"AwardDate":"2012-01-01","AMIUnits":{"lte20":0,"ami30":0,"ami40":0,"ami50":0,"ami60":130,"ami70":0,"ami80":0,"ami100":0,"ami120":0},"PopulationUnits":{"senior":130,"family":0,"homeless":0,"veteran":0,"supportive":0,"special":0}}},{"type":"Feature","geometry":{"type":"Point","coordinates":[-104.847984,39.741766]},"properties":{"PROJECT":"Tiara Apartments","PROJ_ADD":"12000 E. 16th Ave.","PROJ_CTY":"Aurora","PROJ_ST":"CO","CNTY_NAME":"Adams","CNTY_FIPS":"08001","STATEFP":"08","COUNTYFP":"001","N_UNITS":50,"LI_UNITS":50,"YR_PIS":2024,"YR_ALLOC":2024,"CREDIT":"4% and State","NON_PROF":null,"QCT":null,"DDA":null,"_source":"CHFA HousingTaxCreditProperties_view","ReportedName":"Tiara Apartments","ComplianceStatus":"Active Compliance","ProjectType":"Acquisition/Rehabilitation","TypeOfCredits":"4% and State","UrbanRural":"Urban","Region":"Denver Metro","AwardYear":2024,"ReservationYear":2024,"AwardDate":"2024-11-22","AMIUnits":{"lte20":0,"ami30":10,"ami40":0,"ami50":15,"ami60":25,"ami70":0,"ami80":0,"ami100":0,"ami120":0},"PopulationUnits":{"senior":50,"family":0,"homeless":0,"veteran":0,"supportive":0,"special":0}}},{"type":"Feature","geometry":{"type":"Point","coordinates":[-104.84632,39.76134]},"properties":{"PROJECT":"Peoria Crossing Phase II","PROJ_ADD":"3150 N Peoria St.","PROJ_CTY":"Aurora","PROJ_ST":"CO","CNTY_NAME":"Adams","CNTY_FIPS":"08001","STATEFP":"08","COUNTYFP":"001","N_UNITS":72,"LI_UNITS":72,"YR_PIS":2021,"YR_ALLOC":2021,"CREDIT":"4% and State","NON_PROF":null,"QCT":null,"DDA":null,"_source":"CHFA HousingTaxCreditProperties_view","ReportedName":"Peoria Crossing Phase II","ComplianceStatus":"Active Compliance","ProjectType":"New Construction","TypeOfCredits":"4% and State","UrbanRural":"Urban","Region":"Denver Metro","AwardYear":2021,"ReservationYear":2021,"AwardDate":"2021-11-01","AMIUnits":{"lte20":0,"ami30":8,"ami40":6,"ami50":20,"ami60":38,"ami70":0,"ami80":0,"ami100":0,"ami120":0},"PopulationUnits":{"senior":0,"family":72,"homeless":0,"veteran":0,"supportive":0,"special":0}}},{"type":"Feature","geometry":{"type":"Point","coordinates":[-104.961483,39.883448]},"properties":{"PROJECT":"Village of Yorkshire Apartments","PROJ_ADD":"10370 Brendon Way","PROJ_CTY":"Thornton","PROJ_ST":"CO","CNTY_NAME":"Adams","CNTY_FIPS":"08001","STATEFP":"08","COUNTYFP":"001","N_UNITS":200,"LI_UNITS":200,"YR_PIS":2013,"YR_ALLOC":2013,"CREDIT":"4% Tax Exempt","NON_PROF":null,"QCT":null,"DDA":null,"_source":"CHFA HousingTaxCreditProperties_view","ReportedName":"Village of Yorkshire Apartments","ComplianceStatus":"Active Compliance","ProjectType":"Acquisition/Rehabilitation","TypeOfCredits":"4% Tax Exempt","UrbanRural":"Urban","Region":"Denver Metro","AwardYear":2013,"ReservationYear":2013,"AwardDate":"2013-01-01","AMIUnits":{"lte20":0,"ami30":10,"ami40":20,"ami50":60,"ami60":110,"ami70":0,"ami80":0,"ami100":0,"ami120":0},"PopulationUnits":{"senior":0,"family":200,"homeless":0,"veteran":0,"supportive":0,"special":0}}},{"type":"Feature","geometry":{"type":"Point","coordinates":[-104.96635,39.83862]},"properties":{"PROJECT":"Springbrook Apartments","PROJ_ADD":"2021 East 78 Avenue","PROJ_CTY":"Denver","PROJ_ST":"CO","CNTY_NAME":"Adams","CNTY_FIPS":"08001","STATEFP":"08","COUNTYFP":"001","N_UNITS":120,"LI_UNITS":119,"YR_PIS":2003,"YR_ALLOC":2003,"CREDIT":"9% Competitive","NON_PROF":null,"QCT":null,"DDA":null,"_source":"CHFA HousingTaxCreditProperties_view","ReportedName":"Springbrook Apartments","ComplianceStatus":"Active Compliance","ProjectType":"New Construction","TypeOfCredits":"9% Competitive","UrbanRural":"Urban","Region":"Denver Metro","AwardYear":2003,"ReservationYear":2003,"AwardDate":"2003-01-01","AMIUnits":{"lte20":0,"ami30":0,"ami40":71,"ami50":48,"ami60":0,"ami70":0,"ami80":0,"ami100":1,"ami120":0},"PopulationUnits":{"senior":0,"family":120,"homeless":0,"veteran":0,"supportive":0,"special":0}}},{"type":"Feature","geometry":{"type":"Point","coordinates":[-104.84612,39.74458]},"properties":{"PROJECT":"Renaissance Veterans Apartments at Fitzsimons","PROJ_ADD":"1753 N. Quentin Street","PROJ_CTY":"Aurora","PROJ_ST":"CO","CNTY_NAME":"Adams","CNTY_FIPS":"08001","STATEFP":"08","COUNTYFP":"001","N_UNITS":60,"LI_UNITS":59,"YR_PIS":2018,"YR_ALLOC":2018,"CREDIT":"9% Competitive","NON_PROF":null,"QCT":null,"DDA":null,"_source":"CHFA HousingTaxCreditProperties_view","ReportedName":"Renaissance Veterans Apartments at Fitzsimons","ComplianceStatus":"Active Compliance","ProjectType":"New Construction","TypeOfCredits":"9% Competitive","UrbanRural":"Urban","Region":"Denver Metro","AwardYear":2018,"ReservationYear":2018,"AwardDate":"2018-09-14","AMIUnits":{"lte20":0,"ami30":28,"ami40":11,"ami50":10,"ami60":10,"ami70":0,"ami80":0,"ami100":0,"ami120":0},"PopulationUnits":{"senior":0,"family":0,"homeless":30,"veteran":59,"supportive":0,"special":15}}},{"type":"Feature","geometry":{"type":"Point","coordinates":[-104.938415,39.883911]},"properties":{"PROJECT":"Crossing Pointe South","PROJ_ADD":"4220 E.104th Avenue, Bldgs 2&3","PROJ_CTY":"Thornton","PROJ_ST":"CO","CNTY_NAME":"Adams","CNTY_FIPS":"08001","STATEFP":"08","COUNTYFP":"001","N_UNITS":142,"LI_UNITS":142,"YR_PIS":2020,"YR_ALLOC":2020,"CREDIT":"4% Tax Exempt","NON_PROF":null,"QCT":null,"DDA":null,"_source":"CHFA HousingTaxCreditProperties_view","ReportedName":"Crossing Pointe South","ComplianceStatus":"Active Compliance","ProjectType":"New Construction","TypeOfCredits":"4% Tax Exempt","UrbanRural":"Urban","Region":"Denver Metro","AwardYear":2020,"ReservationYear":2020,"AwardDate":"2020-11-03","AMIUnits":{"lte20":0,"ami30":17,"ami40":17,"ami50":43,"ami60":8,"ami70":57,"ami80":0,"ami100":0,"ami120":0},"PopulationUnits":{"senior":0,"family":142,"homeless":0,"veteran":0,"supportive":0,"special":0}}},{"type":"Feature","geometry":{"type":"Point","coordinates":[-104.97321,39.85412]},"properties":{"PROJECT":"Dawson Square","PROJ_ADD":"8670 Dawson Street","PROJ_CTY":"Thornton","PROJ_ST":"CO","CNTY_NAME":"Adams","CNTY_FIPS":"08001","STATEFP":"08","COUNTYFP":"001","N_UNITS":36,"LI_UNITS":35,"YR_PIS":2002,"YR_ALLOC":2002,"CREDIT":"4% Tax Exempt","NON_PROF":null,"QCT":null,"DDA":null,"_source":"CHFA HousingTaxCreditProperties_view","ReportedName":"Dawson Square","ComplianceStatus":"Active Compliance","ProjectType":"Acquisition/Rehabilitation","TypeOfCredits":"4% Tax Exempt","UrbanRural":"Urban","Region":"Denver Metro","AwardYear":2002,"ReservationYear":2002,"AwardDate":"2002-01-01","AMIUnits":{"lte20":0,"ami30":0,"ami40":0,"ami50":0,"ami60":35,"ami70":0,"ami80":0,"ami100":1,"ami120":0},"PopulationUnits":{"senior":0,"family":36,"homeless":0,"veteran":0,"supportive":0,"special":0}}},{"type":"Feature","geometry":{"type":"Point","coordinates":[-104.78967,39.97676]},"properties":{"PROJECT":"Ravenfield","PROJ_ADD":"590 S. 27th Ave.","PROJ_CTY":"Brighton","PROJ_ST":"CO","CNTY_NAME":"Adams","CNTY_FIPS":"08001","STATEFP":"08","COUNTYFP":"001","N_UNITS":46,"LI_UNITS":46,"YR_PIS":2025,"YR_ALLOC":2025,"CREDIT":"9% and State","NON_PROF":null,"QCT":null,"DDA":null,"_source":"CHFA HousingTaxCreditProperties_view","ReportedName":"Ravenfield","ComplianceStatus":"Pre-Compliance - Construction Phase","ProjectType":"New Construction","TypeOfCredits":"9% and State","UrbanRural":"Urban","Region":"Denver Metro","AwardYear":2025,"ReservationYear":2025,"AwardDate":"2025-05-01","AMIUnits":{"lte20":0,"ami30":9,"ami40":0,"ami50":11,"ami60":26,"ami70":0,"ami80":0,"ami100":0,"ami120":0},"PopulationUnits":{"senior":46,"family":0,"homeless":0,"veteran":0,"supportive":0,"special":0}}},{"type":"Feature","geometry":{"type":"Point","coordinates":[-104.938415,39.883911]},"properties":{"PROJECT":"Crossing Pointe North","PROJ_ADD":"4220 E 104th Ave.","PROJ_CTY":"Thornton","PROJ_ST":"CO","CNTY_NAME":"Adams","CNTY_FIPS":"08001","STATEFP":"08","COUNTYFP":"001","N_UNITS":64,"LI_UNITS":64,"YR_PIS":2017,"YR_ALLOC":2017,"CREDIT":"9% Competitive","NON_PROF":null,"QCT":null,"DDA":null,"_source":"CHFA HousingTaxCreditProperties_view","ReportedName":"Crossing Pointe North","ComplianceStatus":"Active Compliance","ProjectType":"New Construction","TypeOfCredits":"9% Competitive","UrbanRural":"Urban","Region":"Denver Metro","AwardYear":2017,"ReservationYear":2017,"AwardDate":"2017-09-01","AMIUnits":{"lte20":0,"ami30":7,"ami40":9,"ami50":33,"ami60":15,"ami70":0,"ami80":0,"ami100":0,"ami120":0},"PopulationUnits":{"senior":64,"family":0,"homeless":0,"veteran":0,"supportive":0,"special":0}}},{"type":"Feature","geometry":{"type":"Point","coordinates":[-105.017822,39.8479]},"properties":{"PROJECT":"Vistas at Panorama Pointe","PROJ_ADD":"8305 Alcott Street","PROJ_CTY":"Westminster","PROJ_ST":"CO","CNTY_NAME":"Adams","CNTY_FIPS":"08001","STATEFP":"08","COUNTYFP":"001","N_UNITS":69,"LI_UNITS":69,"YR_PIS":2016,"YR_ALLOC":2016,"CREDIT":"4% and State","NON_PROF":null,"QCT":null,"DDA":null,"_source":"CHFA HousingTaxCreditProperties_view","ReportedName":"Vistas at Panorama Pointe","ComplianceStatus":"Active Compliance","ProjectType":"New Construction","TypeOfCredits":"4% and State","UrbanRural":"Urban","Region":"Denver Metro","AwardYear":2016,"ReservationYear":2016,"AwardDate":"2016-05-11","AMIUnits":{"lte20":0,"ami30":4,"ami40":0,"ami50":0,"ami60":65,"ami70":0,"ami80":0,"ami100":0,"ami120":0},"PopulationUnits":{"senior":69,"family":0,"homeless":0,"veteran":0,"supportive":0,"special":0}}},{"type":"Feature","geometry":{"type":"Point","coordinates":[-104.831631,39.976333]},"properties":{"PROJECT":"Park Ridge Apartments Platte Valley Terrace","PROJ_ADD":"611 Miller Avenue","PROJ_CTY":"Brighton","PROJ_ST":"CO","CNTY_NAME":"Adams","CNTY_FIPS":"08001","STATEFP":"08","COUNTYFP":"001","N_UNITS":46,"LI_UNITS":45,"YR_PIS":2021,"YR_ALLOC":2021,"CREDIT":"4% and State","NON_PROF":null,"QCT":null,"DDA":null,"_source":"CHFA HousingTaxCreditProperties_view","ReportedName":"Park Ridge Apartments Platte Valley Terrace","ComplianceStatus":"Active Compliance","ProjectType":"Acquisition/Rehabilitation","TypeOfCredits":"4% and State","UrbanRural":"Urban","Region":"Denver Metro","AwardYear":2021,"ReservationYear":2021,"AwardDate":"2021-11-01","AMIUnits":{"lte20":0,"ami30":8,"ami40":0,"ami50":2,"ami60":30,"ami70":0,"ami80":5,"ami100":0,"ami120":0},"PopulationUnits":{"senior":0,"family":45,"homeless":0,"veteran":0,"supportive":0,"special":0}}},{"type":"Feature","geometry":{"type":"Point","coordinates":[-105.03413,39.81346]},"properties":{"PROJECT":"Baker School Apartments","PROJ_ADD":"3555 West 64th Avenue","PROJ_CTY":"Denver","PROJ_ST":"CO","CNTY_NAME":"Adams","CNTY_FIPS":"08001","STATEFP":"08","COUNTYFP":"001","N_UNITS":142,"LI_UNITS":142,"YR_PIS":2017,"YR_ALLOC":2016,"CREDIT":"4% Tax Exempt","NON_PROF":null,"QCT":null,"DDA":null,"_source":"CHFA HousingTaxCreditProperties_view","ReportedName":"Baker School Apartments","ComplianceStatus":"Active Compliance","ProjectType":"New Construction","TypeOfCredits":"4% Tax Exempt","UrbanRural":"Urban","Region":"Denver Metro","AwardYear":2017,"ReservationYear":2016,"AwardDate":"2017-05-02","AMIUnits":{"lte20":0,"ami30":8,"ami40":4,"ami50":3,"ami60":127,"ami70":0,"ami80":0,"ami100":0,"ami120":0},"PopulationUnits":{"senior":0,"family":142,"homeless":0,"veteran":0,"supportive":0,"special":0}}},{"type":"Feature","geometry":{"type":"Point","coordinates":[-104.761986,39.799804]},"properties":{"PROJECT":"Meadows at Dunkirk","PROJ_ADD":"19300 E. 57th Ave.","PROJ_CTY":"Aurora","PROJ_ST":"CO","CNTY_NAME":"Adams","CNTY_FIPS":"08001","STATEFP":"08","COUNTYFP":"001","N_UNITS":204,"LI_UNITS":204,"YR_PIS":2013,"YR_ALLOC":2013,"CREDIT":"4% Tax Exempt","NON_PROF":null,"QCT":null,"DDA":null,"_source":"CHFA HousingTaxCreditProperties_view","ReportedName":"Meadows at Dunkirk","ComplianceStatus":"Active Compliance","ProjectType":"New Construction","TypeOfCredits":"4% Tax Exempt","UrbanRural":"Urban","Region":"Denver Metro","AwardYear":2013,"ReservationYear":2013,"AwardDate":"2013-01-01","AMIUnits":{"lte20":0,"ami30":0,"ami40":0,"ami50":0,"ami60":204,"ami70":0,"ami80":0,"ami100":0,"ami120":0},"PopulationUnits":{"senior":0,"family":204,"homeless":0,"veteran":0,"supportive":0,"special":0}}},{"type":"Feature","geometry":{"type":"Point","coordinates":[-105.002645,39.855369]},"properties":{"PROJECT":"Aztec Villas Apartments","PROJ_ADD":"8675 Mariposa Street","PROJ_CTY":"Thornton","PROJ_ST":"CO","CNTY_NAME":"Adams","CNTY_FIPS":"08001","STATEFP":"08","COUNTYFP":"001","N_UNITS":164,"LI_UNITS":164,"YR_PIS":2015,"YR_ALLOC":2015,"CREDIT":"4% Tax Exempt","NON_PROF":null,"QCT":null,"DDA":null,"_source":"CHFA HousingTaxCreditProperties_view","ReportedName":"Aztec Villas Apartments","ComplianceStatus":"Active Compliance","ProjectType":"Acquisition/Rehabilitation","TypeOfCredits":"4% Tax Exempt","UrbanRural":"Urban","Region":"Denver Metro","AwardYear":2015,"ReservationYear":2015,"AwardDate":"2015-07-15","AMIUnits":{"lte20":0,"ami30":0,"ami40":0,"ami50":0,"ami60":164,"ami70":0,"ami80":0,"ami100":0,"ami120":0},"PopulationUnits":{"senior":0,"family":164,"homeless":0,"veteran":0,"supportive":0,"special":0}}},{"type":"Feature","geometry":{"type":"Point","coordinates":[-104.82054,39.7479]},"properties":{"PROJECT":"Range View Apartments","PROJ_ADD":"14475 E Montview Blvd","PROJ_CTY":"Aurora","PROJ_ST":"CO","CNTY_NAME":"Adams","CNTY_FIPS":"08001","STATEFP":"08","COUNTYFP":"001","N_UNITS":223,"LI_UNITS":220,"YR_PIS":2019,"YR_ALLOC":2018,"CREDIT":"4% Tax Exempt","NON_PROF":null,"QCT":null,"DDA":null,"_source":"CHFA HousingTaxCreditProperties_view","ReportedName":"Range View Apartments","ComplianceStatus":"Active Compliance","ProjectType":"New Construction","TypeOfCredits":"4% Tax Exempt","UrbanRural":"Urban","Region":"Denver Metro","AwardYear":2019,"ReservationYear":2018,"AwardDate":"2019-01-06","AMIUnits":{"lte20":0,"ami30":12,"ami40":0,"ami50":0,"ami60":172,"ami70":36,"ami80":0,"ami100":0,"ami120":0},"PopulationUnits":{"senior":0,"family":223,"homeless":0,"veteran":0,"supportive":0,"special":0}}},{"type":"Feature","geometry":{"type":"Point","coordinates":[-104.985976,39.904771]},"properties":{"PROJECT":"Reserve at Northglenn","PROJ_ADD":"11450 Community Center Dr.","PROJ_CTY":"Northglenn","PROJ_ST":"CO","CNTY_NAME":"Adams","CNTY_FIPS":"08001","STATEFP":"08","COUNTYFP":"001","N_UNITS":260,"LI_UNITS":260,"YR_PIS":2018,"YR_ALLOC":2017,"CREDIT":"4% Tax Exempt","NON_PROF":null,"QCT":null,"DDA":null,"_source":"CHFA HousingTaxCreditProperties_view","ReportedName":"Reserve at Northglenn","ComplianceStatus":"Active Compliance","ProjectType":"New Construction & Acquisition/Rehabilitation","TypeOfCredits":"4% Tax Exempt","UrbanRural":"Urban","Region":"Denver Metro","AwardYear":2018,"ReservationYear":2017,"AwardDate":"2018-06-12","AMIUnits":{"lte20":0,"ami30":0,"ami40":0,"ami50":0,"ami60":260,"ami70":0,"ami80":0,"ami100":0,"ami120":0},"PopulationUnits":{"senior":0,"family":260,"homeless":0,"veteran":0,"supportive":0,"special":0}}},{"type":"Feature","geometry":{"type":"Point","coordinates":[-105.005599,39.906572]},"properties":{"PROJECT":"Westbury Apartments","PROJ_ADD":"11590 N. Pecos","PROJ_CTY":"Westminster","PROJ_ST":"CO","CNTY_NAME":"Adams","CNTY_FIPS":"08001","STATEFP":"08","COUNTYFP":"001","N_UNITS":227,"LI_UNITS":226,"YR_PIS":1999,"YR_ALLOC":1999,"CREDIT":"4% Tax Exempt","NON_PROF":null,"QCT":null,"DDA":null,"_source":"CHFA HousingTaxCreditProperties_view","ReportedName":"Westbury Apartments","ComplianceStatus":"Active Compliance","ProjectType":"Acquisition/Rehabilitation","TypeOfCredits":"4% Tax Exempt","UrbanRural":"Urban","Region":"Denver Metro","AwardYear":1999,"ReservationYear":1999,"AwardDate":"1999-01-01","AMIUnits":{"lte20":0,"ami30":0,"ami40":0,"ami50":14,"ami60":212,"ami70":0,"ami80":0,"ami100":1,"ami120":0},"PopulationUnits":{"senior":0,"family":227,"homeless":0,"veteran":0,"supportive":0,"special":0}}},{"type":"Feature","geometry":{"type":"Point","coordinates":[-104.76782,39.971853]},"properties":{"PROJECT":"Sterling Park","PROJ_ADD":"4242 Bromley Lane","PROJ_CTY":"Brighton","PROJ_ST":"CO","CNTY_NAME":"Adams","CNTY_FIPS":"08001","STATEFP":"08","COUNTYFP":"001","N_UNITS":128,"LI_UNITS":128,"YR_PIS":2002,"YR_ALLOC":2002,"CREDIT":"4% Tax Exempt","NON_PROF":null,"QCT":null,"DDA":null,"_source":"CHFA HousingTaxCreditProperties_view","ReportedName":"Sterling Park","ComplianceStatus":"Active Compliance","ProjectType":"New Construction","TypeOfCredits":"4% Tax Exempt","UrbanRural":"Urban","Region":"Denver Metro","AwardYear":2002,"ReservationYear":2002,"AwardDate":"2002-01-01","AMIUnits":{"lte20":0,"ami30":0,"ami40":0,"ami50":12,"ami60":116,"ami70":0,"ami80":0,"ami100":0,"ami120":0},"PopulationUnits":{"senior":0,"family":128,"homeless":0,"veteran":0,"supportive":0,"special":0}}},{"type":"Feature","geometry":{"type":"Point","coordinates":[-104.91171,39.806473]},"properties":{"PROJECT":"Conter Estates Senior II","PROJ_ADD":"6600 East 60th Place","PROJ_CTY":"Commerce City","PROJ_ST":"CO","CNTY_NAME":"Adams","CNTY_FIPS":"08001","STATEFP":"08","COUNTYFP":"001","N_UNITS":39,"LI_UNITS":39,"YR_PIS":2008,"YR_ALLOC":2008,"CREDIT":"9% Competitive","NON_PROF":null,"QCT":null,"DDA":null,"_source":"CHFA HousingTaxCreditProperties_view","ReportedName":"Conter Estates Senior II","ComplianceStatus":"Active Compliance","ProjectType":"New Construction","TypeOfCredits":"9% Competitive","UrbanRural":"Urban","Region":"Denver Metro","AwardYear":2008,"ReservationYear":2008,"AwardDate":"2008-01-01","AMIUnits":{"lte20":0,"ami30":4,"ami40":19,"ami50":16,"ami60":0,"ami70":0,"ami80":0,"ami100":0,"ami120":0},"PopulationUnits":{"senior":39,"family":0,"homeless":0,"veteran":0,"supportive":0,"special":0}}},{"type":"Feature","geometry":{"type":"Point","coordinates":[-104.923234,39.805103]},"properties":{"PROJECT":"Holly Park Apartments","PROJ_ADD":"5524 E. 60th Avenue","PROJ_CTY":"Commerce City","PROJ_ST":"CO","CNTY_NAME":"Adams","CNTY_FIPS":"08001","STATEFP":"08","COUNTYFP":"001","N_UNITS":168,"LI_UNITS":168,"YR_PIS":2017,"YR_ALLOC":2017,"CREDIT":"4% Tax Exempt","NON_PROF":null,"QCT":null,"DDA":null,"_source":"CHFA HousingTaxCreditProperties_view","ReportedName":"Holly Park Apartments","ComplianceStatus":"Active Compliance","ProjectType":"Acquisition/Rehabilitation","TypeOfCredits":"4% Tax Exempt","UrbanRural":"Urban","Region":"Denver Metro","AwardYear":2017,"ReservationYear":2017,"AwardDate":"2017-05-23","AMIUnits":{"lte20":0,"ami30":0,"ami40":0,"ami50":149,"ami60":19,"ami70":0,"ami80":0,"ami100":0,"ami120":0},"PopulationUnits":{"senior":0,"family":168,"homeless":0,"veteran":0,"supportive":0,"special":0}}},{"type":"Feature","geometry":{"type":"Point","coordinates":[-105.000005,39.821571]},"properties":{"PROJECT":"Casa Redonda de Vigil","PROJ_ADD":"1080 W. 69th Ave.","PROJ_CTY":"Denver","PROJ_ST":"CO","CNTY_NAME":"Adams","CNTY_FIPS":"08001","STATEFP":"08","COUNTYFP":"001","N_UNITS":42,"LI_UNITS":42,"YR_PIS":2021,"YR_ALLOC":2021,"CREDIT":"4% Tax Exempt","NON_PROF":null,"QCT":null,"DDA":null,"_source":"CHFA HousingTaxCreditProperties_view","ReportedName":"Casa Redonda de Vigil","ComplianceStatus":"Active Compliance","ProjectType":"Acquisition/Rehabilitation","TypeOfCredits":"4% Tax Exempt","UrbanRural":"Urban","Region":"Denver Metro","AwardYear":2021,"ReservationYear":2021,"AwardDate":"2021-07-20","AMIUnits":{"lte20":0,"ami30":0,"ami40":0,"ami50":0,"ami60":42,"ami70":0,"ami80":0,"ami100":0,"ami120":0},"PopulationUnits":{"senior":42,"family":0,"homeless":0,"veteran":0,"supportive":0,"special":0}}},{"type":"Feature","geometry":{"type":"Point","coordinates":[-104.821196,39.991622]},"properties":{"PROJECT":"Hughes Station","PROJ_ADD":"233 North Main Street","PROJ_CTY":"Brighton","PROJ_ST":"CO","CNTY_NAME":"Adams","CNTY_FIPS":"08001","STATEFP":"08","COUNTYFP":"001","N_UNITS":120,"LI_UNITS":120,"YR_PIS":2024,"YR_ALLOC":2023,"CREDIT":"4% Tax Exempt","NON_PROF":null,"QCT":null,"DDA":null,"_source":"CHFA HousingTaxCreditProperties_view","ReportedName":"Hughes Station","ComplianceStatus":"Active Compliance","ProjectType":"Acquisition/Rehabilitation","TypeOfCredits":"4% Tax Exempt","UrbanRural":"Urban","Region":"Denver Metro","AwardYear":2024,"ReservationYear":2023,"AwardDate":"2024-06-04","AMIUnits":{"lte20":0,"ami30":18,"ami40":18,"ami50":51,"ami60":33,"ami70":0,"ami80":0,"ami100":0,"ami120":0},"PopulationUnits":{"senior":0,"family":120,"homeless":0,"veteran":0,"supportive":0,"special":0}}},{"type":"Feature","geometry":{"type":"Point","coordinates":[-104.93919,39.82695]},"properties":{"PROJECT":"SP Crossing","PROJ_ADD":"7130 Colorado Boulevard","PROJ_CTY":"Commerce City","PROJ_ST":"CO","CNTY_NAME":"Adams","CNTY_FIPS":"08001","STATEFP":"08","COUNTYFP":"001","N_UNITS":60,"LI_UNITS":60,"YR_PIS":2022,"YR_ALLOC":2022,"CREDIT":"9% Competitive","NON_PROF":null,"QCT":null,"DDA":null,"_source":"CHFA HousingTaxCreditProperties_view","ReportedName":"SP Crossing","ComplianceStatus":"Active Compliance","ProjectType":"New Construction","TypeOfCredits":"9% Competitive","UrbanRural":"Urban","Region":"Denver Metro","AwardYear":2022,"ReservationYear":2022,"AwardDate":"2022-05-05","AMIUnits":{"lte20":0,"ami30":8,"ami40":12,"ami50":22,"ami60":0,"ami70":6,"ami80":12,"ami100":0,"ami120":0},"PopulationUnits":{"senior":0,"family":60,"homeless":0,"veteran":0,"supportive":0,"special":0}}},{"type":"Feature","geometry":{"type":"Point","coordinates":[-104.802134,39.740948]},"properties":{"PROJECT":"Crossbar Commons","PROJ_ADD":"15961 E. Colfax Avenue","PROJ_CTY":"Aurora","PROJ_ST":"CO","CNTY_NAME":"Adams","CNTY_FIPS":"08001","STATEFP":"08","COUNTYFP":"001","N_UNITS":104,"LI_UNITS":104,"YR_PIS":2025,"YR_ALLOC":2025,"CREDIT":"4% and State and TOC","NON_PROF":null,"QCT":null,"DDA":null,"_source":"CHFA HousingTaxCreditProperties_view","ReportedName":"Crossbar Commons","ComplianceStatus":"Pre-Compliance - Construction Phase","ProjectType":"New Construction","TypeOfCredits":"4% and State and TOC","UrbanRural":"Urban","Region":"Denver Metro","AwardYear":2025,"ReservationYear":2025,"AwardDate":"2025-10-31","AMIUnits":{"lte20":0,"ami30":6,"ami40":0,"ami50":98,"ami60":0,"ami70":0,"ami80":0,"ami100":0,"ami120":0},"PopulationUnits":{"senior":0,"family":104,"homeless":0,"veteran":0,"supportive":0,"special":0}}},{"type":"Feature","geometry":{"type":"Point","coordinates":[-104.972942,39.918662]},"properties":{"PROJECT":"InnovAge Senior Housing Thornton","PROJ_ADD":"12201 Washington Center Parkway","PROJ_CTY":"Thornton","PROJ_ST":"CO","CNTY_NAME":"Adams","CNTY_FIPS":"08001","STATEFP":"08","COUNTYFP":"001","N_UNITS":72,"LI_UNITS":72,"YR_PIS":2012,"YR_ALLOC":2012,"CREDIT":"9% Competitive","NON_PROF":null,"QCT":null,"DDA":null,"_source":"CHFA HousingTaxCreditProperties_view","ReportedName":"InnovAge Senior Housing Thornton","ComplianceStatus":"Active Compliance","ProjectType":"New Construction","TypeOfCredits":"9% Competitive","UrbanRural":"Urban","Region":"Denver Metro","AwardYear":2012,"ReservationYear":2012,"AwardDate":"2012-01-01","AMIUnits":{"lte20":0,"ami30":8,"ami40":15,"ami50":30,"ami60":19,"ami70":0,"ami80":0,"ami100":0,"ami120":0},"PopulationUnits":{"senior":72,"family":0,"homeless":0,"veteran":0,"supportive":0,"special":0}}},{"type":"Feature","geometry":{"type":"Point","coordinates":[-104.824424,39.980612]},"properties":{"PROJECT":"Brighton Village Phase II","PROJ_ADD":"197 W Southern Street","PROJ_CTY":"Brighton","PROJ_ST":"CO","CNTY_NAME":"Adams","CNTY_FIPS":"08001","STATEFP":"08","COUNTYFP":"001","N_UNITS":63,"LI_UNITS":63,"YR_PIS":2015,"YR_ALLOC":2015,"CREDIT":"9% Competitive","NON_PROF":null,"QCT":null,"DDA":null,"_source":"CHFA HousingTaxCreditProperties_view","ReportedName":"Brighton Village Phase II","ComplianceStatus":"Active Compliance","ProjectType":"New Construction","TypeOfCredits":"9% Competitive","UrbanRural":"Urban","Region":"Denver Metro","AwardYear":2015,"ReservationYear":2015,"AwardDate":"2015-01-01","AMIUnits":{"lte20":0,"ami30":20,"ami40":27,"ami50":11,"ami60":5,"ami70":0,"ami80":0,"ami100":0,"ami120":0},"PopulationUnits":{"senior":63,"family":0,"homeless":0,"veteran":0,"supportive":0,"special":0}}},{"type":"Feature","geometry":{"type":"Point","coordinates":[-104.874456,39.74071]},"properties":{"PROJECT":"Florence Square II","PROJ_ADD":"1523 N. Emporia Street","PROJ_CTY":"Aurora","PROJ_ST":"CO","CNTY_NAME":"Adams","CNTY_FIPS":"08001","STATEFP":"08","COUNTYFP":"001","N_UNITS":71,"LI_UNITS":71,"YR_PIS":2006,"YR_ALLOC":2006,"CREDIT":"9% Competitive","NON_PROF":null,"QCT":null,"DDA":null,"_source":"CHFA HousingTaxCreditProperties_view","ReportedName":"Florence Square II","ComplianceStatus":"Active Compliance","ProjectType":"New Construction","TypeOfCredits":"9% Competitive","UrbanRural":"Urban","Region":"Denver Metro","AwardYear":2006,"ReservationYear":2006,"AwardDate":"2006-01-01","AMIUnits":{"lte20":0,"ami30":0,"ami40":27,"ami50":44,"ami60":0,"ami70":0,"ami80":0,"ami100":0,"ami120":0},"PopulationUnits":{"senior":0,"family":71,"homeless":0,"veteran":0,"supportive":0,"special":0}}},{"type":"Feature","geometry":{"type":"Point","coordinates":[-105.05235,39.85128]},"properties":{"PROJECT":"Toscana Apartments","PROJ_ADD":"8490 N. Sheridan","PROJ_CTY":"Westminster","PROJ_ST":"CO","CNTY_NAME":"Adams","CNTY_FIPS":"08001","STATEFP":"08","COUNTYFP":"001","N_UNITS":252,"LI_UNITS":252,"YR_PIS":2004,"YR_ALLOC":2004,"CREDIT":"4% Tax Exempt","NON_PROF":null,"QCT":null,"DDA":null,"_source":"CHFA HousingTaxCreditProperties_view","ReportedName":"Toscana Apartments","ComplianceStatus":"Active Compliance","ProjectType":"Acquisition/Rehabilitation","TypeOfCredits":"4% Tax Exempt","UrbanRural":"Urban","Region":"Denver Metro","AwardYear":2004,"ReservationYear":2004,"AwardDate":"2004-01-01","AMIUnits":{"lte20":0,"ami30":0,"ami40":0,"ami50":25,"ami60":227,"ami70":0,"ami80":0,"ami100":0,"ami120":0},"PopulationUnits":{"senior":0,"family":252,"homeless":0,"veteran":0,"supportive":0,"special":0}}},{"type":"Feature","geometry":{"type":"Point","coordinates":[-104.91171,39.806473]},"properties":{"PROJECT":"Conter Estates Senior Apartments","PROJ_ADD":"6600 East 60th Place","PROJ_CTY":"Commerce City","PROJ_ST":"CO","CNTY_NAME":"Adams","CNTY_FIPS":"08001","STATEFP":"08","COUNTYFP":"001","N_UNITS":75,"LI_UNITS":74,"YR_PIS":2002,"YR_ALLOC":2002,"CREDIT":"9% Competitive","NON_PROF":null,"QCT":null,"DDA":null,"_source":"CHFA HousingTaxCreditProperties_view","ReportedName":"Conter Estates Senior Apartments","ComplianceStatus":"Active Compliance","ProjectType":"New Construction","TypeOfCredits":"9% Competitive","UrbanRural":"Urban","Region":"Denver Metro","AwardYear":2002,"ReservationYear":2002,"AwardDate":"2002-01-01","AMIUnits":{"lte20":0,"ami30":0,"ami40":45,"ami50":29,"ami60":0,"ami70":0,"ami80":0,"ami100":1,"ami120":0},"PopulationUnits":{"senior":75,"family":0,"homeless":0,"veteran":0,"supportive":0,"special":0}}},{"type":"Feature","geometry":{"type":"Point","coordinates":[-104.98124,39.98861]},"properties":{"PROJECT":"Larkridge Apartments","PROJ_ADD":"16105 Washington St.","PROJ_CTY":"Thornton","PROJ_ST":"CO","CNTY_NAME":"Adams","CNTY_FIPS":"08001","STATEFP":"08","COUNTYFP":"001","N_UNITS":338,"LI_UNITS":338,"YR_PIS":2017,"YR_ALLOC":2017,"CREDIT":"4% Tax Exempt","NON_PROF":null,"QCT":null,"DDA":null,"_source":"CHFA HousingTaxCreditProperties_view","ReportedName":"Larkridge Apartments","ComplianceStatus":"Active Compliance","ProjectType":"New Construction","TypeOfCredits":"4% Tax Exempt","UrbanRural":"Urban","Region":"Denver Metro","AwardYear":2017,"ReservationYear":2017,"AwardDate":"2017-12-12","AMIUnits":{"lte20":0,"ami30":0,"ami40":0,"ami50":0,"ami60":338,"ami70":0,"ami80":0,"ami100":0,"ami120":0},"PopulationUnits":{"senior":0,"family":338,"homeless":0,"veteran":0,"supportive":0,"special":0}}},{"type":"Feature","geometry":{"type":"Point","coordinates":[-104.824,39.747527]},"properties":{"PROJECT":"Fitzsimmons Junction","PROJ_ADD":"14155 East Montview Boulevard","PROJ_CTY":"Aurora","PROJ_ST":"CO","CNTY_NAME":"Adams","CNTY_FIPS":"08001","STATEFP":"08","COUNTYFP":"001","N_UNITS":126,"LI_UNITS":125,"YR_PIS":1997,"YR_ALLOC":1997,"CREDIT":"4% Tax Exempt","NON_PROF":null,"QCT":null,"DDA":null,"_source":"CHFA HousingTaxCreditProperties_view","ReportedName":"Fitzsimmons Junction","ComplianceStatus":"Active Compliance","ProjectType":"Acquisition/Rehabilitation","TypeOfCredits":"4% Tax Exempt","UrbanRural":"Urban","Region":"Denver Metro","AwardYear":1997,"ReservationYear":1997,"AwardDate":"1997-01-01","AMIUnits":{"lte20":0,"ami30":0,"ami40":0,"ami50":0,"ami60":125,"ami70":0,"ami80":0,"ami100":1,"ami120":0},"PopulationUnits":{"senior":0,"family":126,"homeless":0,"veteran":0,"supportive":0,"special":0}}},{"type":"Feature","geometry":{"type":"Point","coordinates":[-104.80934,39.68238]},"properties":{"PROJECT":"Wagoner on the Creek","PROJ_ADD":"1900 S. Chambers Road","PROJ_CTY":"Aurora","PROJ_ST":"CO","CNTY_NAME":"Adams","CNTY_FIPS":"08001","STATEFP":"08","COUNTYFP":"001","N_UNITS":60,"LI_UNITS":60,"YR_PIS":2025,"YR_ALLOC":2025,"CREDIT":"9% and State and TOC","NON_PROF":null,"QCT":null,"DDA":null,"_source":"CHFA HousingTaxCreditProperties_view","ReportedName":"Wagoner on the Creek","ComplianceStatus":"Active Compliance","ProjectType":"New Construction","TypeOfCredits":"9% and State and TOC","UrbanRural":"Urban","Region":"Denver Metro","AwardYear":2025,"ReservationYear":2025,"AwardDate":"2025-05-01","AMIUnits":{"lte20":0,"ami30":60,"ami40":0,"ami50":0,"ami60":0,"ami70":0,"ami80":0,"ami100":0,"ami120":0},"PopulationUnits":{"senior":0,"family":0,"homeless":0,"veteran":0,"supportive":60,"special":0}}},{"type":"Feature","geometry":{"type":"Point","coordinates":[-104.02457,39.85598]},"properties":{"PROJECT":"Verrbena","PROJ_ADD":"2880 W. 88th Ave","PROJ_CTY":"Westminster","PROJ_ST":"CO","CNTY_NAME":"Adams","CNTY_FIPS":"08001","STATEFP":"08","COUNTYFP":"001","N_UNITS":70,"LI_UNITS":70,"YR_PIS":2024,"YR_ALLOC":2024,"CREDIT":"4% and State","NON_PROF":null,"QCT":null,"DDA":null,"_source":"CHFA HousingTaxCreditProperties_view","ReportedName":"Verrbena","ComplianceStatus":"Active Compliance","ProjectType":"New Construction","TypeOfCredits":"4% and State","UrbanRural":"Urban","Region":"Denver Metro","AwardYear":2024,"ReservationYear":2024,"AwardDate":"2024-11-22","AMIUnits":{"lte20":0,"ami30":18,"ami40":11,"ami50":19,"ami60":0,"ami70":22,"ami80":0,"ami100":0,"ami120":0},"PopulationUnits":{"senior":0,"family":52,"homeless":0,"veteran":0,"supportive":0,"special":18}}},{"type":"Feature","geometry":{"type":"Point","coordinates":[-104.812641,39.969392]},"properties":{"PROJECT":"Windmill Ranch Apartments","PROJ_ADD":"1083 S. 8th Ave.","PROJ_CTY":"Brighton","PROJ_ST":"CO","CNTY_NAME":"Adams","CNTY_FIPS":"08001","STATEFP":"08","COUNTYFP":"001","N_UNITS":96,"LI_UNITS":96,"YR_PIS":2016,"YR_ALLOC":2016,"CREDIT":"4% and State","NON_PROF":null,"QCT":null,"DDA":null,"_source":"CHFA HousingTaxCreditProperties_view","ReportedName":"Windmill Ranch Apartments","ComplianceStatus":"Active Compliance","ProjectType":"New Construction","TypeOfCredits":"4% and State","UrbanRural":"Urban","Region":"Denver Metro","AwardYear":2016,"ReservationYear":2016,"AwardDate":"2016-05-11","AMIUnits":{"lte20":0,"ami30":15,"ami40":12,"ami50":32,"ami60":37,"ami70":0,"ami80":0,"ami100":0,"ami120":0},"PopulationUnits":{"senior":0,"family":96,"homeless":0,"veteran":0,"supportive":0,"special":0}}},{"type":"Feature","geometry":{"type":"Point","coordinates":[-104.77499,39.76574]},"properties":{"PROJECT":"Walden 35","PROJ_ADD":"3500 Walden St.","PROJ_CTY":"Aurora","PROJ_ST":"CO","CNTY_NAME":"Adams","CNTY_FIPS":"08001","STATEFP":"08","COUNTYFP":"001","N_UNITS":100,"LI_UNITS":100,"YR_PIS":2021,"YR_ALLOC":2021,"CREDIT":"4% Tax Exempt","NON_PROF":null,"QCT":null,"DDA":null,"_source":"CHFA HousingTaxCreditProperties_view","ReportedName":"Walden 35","ComplianceStatus":"Active Compliance","ProjectType":"New Construction","TypeOfCredits":"4% Tax Exempt","UrbanRural":"Urban","Region":"Denver Metro","AwardYear":2021,"ReservationYear":2021,"AwardDate":"2021-05-18","AMIUnits":{"lte20":0,"ami30":5,"ami40":5,"ami50":30,"ami60":40,"ami70":20,"ami80":0,"ami100":0,"ami120":0},"PopulationUnits":{"senior":0,"family":100,"homeless":0,"veteran":0,"supportive":0,"special":0}}},{"type":"Feature","geometry":{"type":"Point","coordinates":[-104.98052,39.90096]},"properties":{"PROJECT":"Glennpark Village","PROJ_ADD":"11230 Grant Drive","PROJ_CTY":"Northglenn","PROJ_ST":"CO","CNTY_NAME":"Adams","CNTY_FIPS":"08001","STATEFP":"08","COUNTYFP":"001","N_UNITS":26,"LI_UNITS":26,"YR_PIS":2024,"YR_ALLOC":2024,"CREDIT":"4% Tax Exempt","NON_PROF":null,"QCT":null,"DDA":null,"_source":"CHFA HousingTaxCreditProperties_view","ReportedName":"Glennpark Village","ComplianceStatus":"Active Compliance","ProjectType":"Acquisition/Rehabilitation","TypeOfCredits":"4% Tax Exempt","UrbanRural":"Urban","Region":"Denver Metro","AwardYear":2024,"ReservationYear":2024,"AwardDate":"2024-09-17","AMIUnits":{"lte20":0,"ami30":0,"ami40":3,"ami50":17,"ami60":6,"ami70":0,"ami80":0,"ami100":0,"ami120":0},"PopulationUnits":{"senior":0,"family":26,"homeless":0,"veteran":0,"supportive":0,"special":0}}},{"type":"Feature","geometry":{"type":"Point","coordinates":[-104.981628,39.855286]},"properties":{"PROJECT":"Rockview Terrace","PROJ_ADD":"388 E. 88th Avenue","PROJ_CTY":"Thornton","PROJ_ST":"CO","CNTY_NAME":"Adams","CNTY_FIPS":"08001","STATEFP":"08","COUNTYFP":"001","N_UNITS":180,"LI_UNITS":178,"YR_PIS":2006,"YR_ALLOC":2006,"CREDIT":"4% Tax Exempt","NON_PROF":null,"QCT":null,"DDA":null,"_source":"CHFA HousingTaxCreditProperties_view","ReportedName":"Rockview Terrace","ComplianceStatus":"Active Compliance","ProjectType":"Acquisition/Rehabilitation","TypeOfCredits":"4% Tax Exempt","UrbanRural":"Urban","Region":"Denver Metro","AwardYear":2006,"ReservationYear":2006,"AwardDate":"2006-01-01","AMIUnits":{"lte20":0,"ami30":0,"ami40":60,"ami50":60,"ami60":58,"ami70":0,"ami80":0,"ami100":2,"ami120":0},"PopulationUnits":{"senior":0,"family":180,"homeless":0,"veteran":0,"supportive":0,"special":0}}},{"type":"Feature","geometry":{"type":"Point","coordinates":[-104.987909,39.830583]},"properties":{"PROJECT":"Caraway","PROJ_ADD":"7401 Broadway","PROJ_CTY":"Denver","PROJ_ST":"CO","CNTY_NAME":"Adams","CNTY_FIPS":"08001","STATEFP":"08","COUNTYFP":"001","N_UNITS":116,"LI_UNITS":116,"YR_PIS":2019,"YR_ALLOC":2019,"CREDIT":"4% and State","NON_PROF":null,"QCT":null,"DDA":null,"_source":"CHFA HousingTaxCreditProperties_view","ReportedName":"Caraway","ComplianceStatus":"Active Compliance","ProjectType":"New Construction & Acquisition/Rehabilitation","TypeOfCredits":"4% and State","UrbanRural":"Urban","Region":"Denver Metro","AwardYear":2019,"ReservationYear":2019,"AwardDate":"2019-05-24","AMIUnits":{"lte20":0,"ami30":8,"ami40":4,"ami50":46,"ami60":0,"ami70":58,"ami80":0,"ami100":0,"ami120":0},"PopulationUnits":{"senior":0,"family":116,"homeless":0,"veteran":0,"supportive":0,"special":0}}},{"type":"Feature","geometry":{"type":"Point","coordinates":[-105.00076,39.86317]},"properties":{"PROJECT":"Creekside Place Apartments","PROJ_ADD":"9189 Gale Blvd.","PROJ_CTY":"Thornton","PROJ_ST":"CO","CNTY_NAME":"Adams","CNTY_FIPS":"08001","STATEFP":"08","COUNTYFP":"001","N_UNITS":208,"LI_UNITS":207,"YR_PIS":1998,"YR_ALLOC":1998,"CREDIT":"4% Tax Exempt","NON_PROF":null,"QCT":null,"DDA":null,"_source":"CHFA HousingTaxCreditProperties_view","ReportedName":"Creekside Place Apartments","ComplianceStatus":"Active Compliance","ProjectType":"Acquisition/Rehabilitation","TypeOfCredits":"4% Tax Exempt","UrbanRural":"Urban","Region":"Denver Metro","AwardYear":1998,"ReservationYear":1998,"AwardDate":"1998-01-01","AMIUnits":{"lte20":0,"ami30":0,"ami40":0,"ami50":0,"ami60":207,"ami70":0,"ami80":0,"ami100":1,"ami120":0},"PopulationUnits":{"senior":0,"family":208,"homeless":0,"veteran":0,"supportive":0,"special":0}}},{"type":"Feature","geometry":{"type":"Point","coordinates":[-104.824768,39.979844]},"properties":{"PROJECT":"Brighton Senior Apartments","PROJ_ADD":"199 W. Southern Street","PROJ_CTY":"Brighton","PROJ_ST":"CO","CNTY_NAME":"Adams","CNTY_FIPS":"08001","STATEFP":"08","COUNTYFP":"001","N_UNITS":60,"LI_UNITS":60,"YR_PIS":2005,"YR_ALLOC":2005,"CREDIT":"9% Competitive","NON_PROF":null,"QCT":null,"DDA":null,"_source":"CHFA HousingTaxCreditProperties_view","ReportedName":"Brighton Senior Apartments","ComplianceStatus":"Active Compliance","ProjectType":"New Construction","TypeOfCredits":"9% Competitive","UrbanRural":"Urban","Region":"Denver Metro","AwardYear":2005,"ReservationYear":2005,"AwardDate":"2005-01-01","AMIUnits":{"lte20":0,"ami30":12,"ami40":24,"ami50":19,"ami60":5,"ami70":0,"ami80":0,"ami100":0,"ami120":0},"PopulationUnits":{"senior":60,"family":0,"homeless":0,"veteran":0,"supportive":0,"special":0}}}]}