{"updated": "2026-02-27T17:50:10Z", "geo": {"type": "cdp", "geoid": "0840377", "label": "Ken Caryl (CDP)"}, "acsProfile": {"DP05_0001E": "33233", "DP02_0001E": "13769", "DP03_0062E": "118269", "DP04_0001E": "13945", "DP04_0047PE": "84.4", "DP04_0046PE": "15.6", "DP04_0089E": "600300", "DP04_0134E": "2127", "DP04_0003E": "8995", "DP04_0004E": "2470", "DP04_0005E": "7", "DP04_0006E": "254", "DP04_0007E": "530", "DP04_0008E": "866", "DP04_0009E": "819", "DP04_0010E": "4", "DP04_0142PE": null, "DP04_0143PE": null, "DP04_0144PE": "14.0", "DP04_0145PE": "9.9", "DP04_0146PE": "32.5", "NAME": "Ken Caryl CDP, Colorado"}, "acsS0801": {"S0801_C01_001E": "18095", "S0801_C01_002E": "69.0", "S0801_C01_003E": "63.0", "S0801_C01_004E": "6.0", "S0801_C01_005E": "4.5", "S0801_C01_006E": "0.7", "S0801_C01_007E": "0.8", "S0801_C01_018E": "100.0", "NAME": "Ken Caryl CDP, Colorado", "state": "08", "place": "40377"}, "source": {"acs_profile_endpoint": "https://api.census.gov/data/2024/acs/acs1/profile", "acs_s0801_endpoint": "https://api.census.gov/data/2024/acs/acs1/subject"}}