{
  "updated": "2026-06-08T11:35:16Z",
  "geo": {
    "type": "place",
    "geoid": "0869040",
    "label": "Seibert (town)",
    "containingCounty": "08063"
  },
  "acsProfile": {
    "DP05_0001E": 138,
    "DP03_0062E": 48750,
    "DP04_0001E": 85,
    "DP04_0046PE": 73.5,
    "DP04_0047PE": 26.5,
    "DP04_0047E": 18,
    "DP04_0089E": 118800,
    "DP04_0134E": 1175,
    "DP04_0005E": 21.7,
    "DP04_0007E": 61,
    "DP04_0008E": 0,
    "DP04_0009E": 0,
    "DP04_0010E": 0,
    "DP04_0011E": 0,
    "DP04_0012E": 0,
    "DP04_0013E": 0,
    "DP04_0014E": 24,
    "DP04_0137PE": 26.7,
    "DP04_0138PE": 33.3,
    "DP04_0139PE": 0,
    "DP04_0140PE": 0,
    "DP04_0141PE": 0,
    "DP04_0142PE": 40,
    "NAME": null,
    "state": 8,
    "place": 69040,
    "DP03_0052E": 2,
    "DP03_0053E": 10,
    "DP03_0054E": 5,
    "DP03_0055E": 7,
    "DP03_0056E": 10,
    "DP03_0057E": 21,
    "DP03_0058E": 6,
    "DP03_0059E": 4,
    "DP03_0060E": 2,
    "DP04_0017E": 1,
    "DP04_0018E": 0,
    "DP04_0019E": 4,
    "DP04_0020E": 3,
    "DP04_0021E": 11,
    "DP04_0022E": 35,
    "DP04_0023E": 1,
    "DP04_0024E": 8,
    "DP04_0025E": 0,
    "DP04_0026E": 22,
    "DP04_0039E": 0,
    "DP04_0040E": 1,
    "DP04_0041E": 21,
    "DP04_0042E": 30,
    "DP04_0043E": 29,
    "DP04_0044E": 4,
    "DP04_0111PE": 33.3,
    "DP04_0112PE": 33.3,
    "DP04_0113PE": 0,
    "DP04_0114PE": 33.3,
    "DP04_0115PE": 0,
    "DP04_0080E": "52",
    "DP04_0081E": "12",
    "DP04_0082E": "20",
    "DP04_0083E": "2",
    "DP04_0084E": "5",
    "DP04_0085E": "6",
    "DP04_0086E": "7",
    "DP04_0087E": "0",
    "DP04_0088E": "0",
    "DP02_0014E": "14",
    "DP02_0016E": "2.30",
    "DP02_0034E": "0",
    "DP02_0035E": "8",
    "DP02_0036E": "10",
    "DP02_0037E": "0",
    "DP02_0038E": "0",
    "DP02_0039E": "0",
    "DP02_0040E": "0",
    "DP03_0027E": "3",
    "DP03_0028E": "13",
    "DP03_0029E": "5",
    "DP03_0030E": "14",
    "DP03_0031E": "12",
    "DP03_0002E": "47",
    "DP03_0005E": "0",
    "DP03_0007E": "82",
    "DP02_0001E": "69",
    "DP02_0002E": "21",
    "DP02_0004E": "12",
    "DP02_0006E": "17",
    "DP02_0007E": "0",
    "DP02_0008E": "17",
    "DP02_0010E": "19",
    "DP02_0011E": "0",
    "DP02_0012E": "13",
    "DP02_0015E": "35",
    "DP02_0017E": "3.17",
    "DP02_0072E": "27",
    "DP02_0059E": "114",
    "DP02_0060E": "3",
    "DP02_0061E": "3",
    "DP02_0062E": "53",
    "DP02_0063E": "34",
    "DP02_0064E": "4",
    "DP02_0065E": "13",
    "DP02_0066E": "4",
    "DP02_0067E": "108",
    "DP02_0068E": "17",
    "DP05_0033E": "159",
    "DP05_0037E": "159",
    "DP05_0038E": "0",
    "DP05_0039E": "0",
    "DP05_0047E": "0",
    "DP05_0055E": "0",
    "DP05_0060E": "0",
    "DP05_0061E": "0",
    "DP05_0076E": "3",
    "DP05_0082E": "156",
    "DP05_0024E": "56",
    "DP05_0029E": "56"
  },
  "acsS0801": {
    "S0801_C01_001E": 50,
    "S0801_C01_002E": 86,
    "S0801_C01_003E": 86,
    "S0801_C01_004E": 0,
    "S0801_C01_005E": 0,
    "S0801_C01_006E": 0,
    "S0801_C01_007E": 0,
    "S0801_C01_008E": 0.96,
    "S0801_C01_018E": 100,
    "NAME": null,
    "state": 8,
    "place": 69040,
    "_acsYear": 2024,
    "_acsSeries": null
  },
  "acsB08301": {
    "total": 50,
    "drive": 43,
    "carpool": 0,
    "transit": 0,
    "bike": 3,
    "walk": 0,
    "other": 0,
    "work_from_home": 4
  },
  "source": {
    "acs_profile_endpoint": "https://api.census.gov/data/2024/acs/acs1/profile",
    "acs_s0801_endpoint": "https://api.census.gov/data/2024/acs/acs5/subject",
    "acs_b08301_endpoint": "https://api.census.gov/data/2024/acs/acs1"
  }
}
