{"updated": "2026-03-01T07:21:01Z", "geo": {"type": "place", "geoid": "0874815", "label": "Sugar City town"}, "acsProfile": {"DP05_0001E": "464", "DP02_0001E": "127", "DP03_0062E": "47798", "DP04_0001E": "156", "DP04_0047PE": "67.7", "DP04_0046PE": "32.3", "DP04_0089E": "90000", "DP04_0134E": "812", "DP04_0003E": "140", "DP04_0004E": "2", "DP04_0005E": "0", "DP04_0006E": "0", "DP04_0007E": "0", "DP04_0008E": "0", "DP04_0009E": "0", "DP04_0010E": "14", "DP04_0142PE": null, "DP04_0143PE": null, "DP04_0144PE": "0.0", "DP04_0145PE": "0.0", "DP04_0146PE": "39.0", "NAME": "Sugar City town, Colorado"}, "acsS0801": {"S0801_C01_001E": "210", "S0801_C01_002E": "93.8", "S0801_C01_003E": "86.7", "S0801_C01_004E": "7.1", "S0801_C01_005E": "7.1", "S0801_C01_006E": "0.0", "S0801_C01_007E": "0.0", "S0801_C01_018E": "100.0", "NAME": "Sugar City town, Colorado", "state": "08", "place": "74815"}, "source": {"acs_profile_endpoint": "https://api.census.gov/data/2024/acs/acs1/profile", "acs_s0801_endpoint": "https://api.census.gov/data/2024/acs/acs1/subject"}}