{"updated": "2026-04-27T08:56:39Z", "geo": {"type": "place", "geoid": "0886090", "label": "Woodland Park (city)", "containingCounty": "08119"}, "acsProfile": {"DP05_0001E": 7949, "DP03_0062E": 99238, "DP04_0001E": 3647, "DP04_0046PE": 76.5, "DP04_0047PE": 23.5, "DP04_0047E": 833, "DP04_0089E": 549200, "DP04_0134E": 2007, "DP04_0005E": 5, "DP04_0007E": 2799, "DP04_0008E": 170, "DP04_0009E": 19, "DP04_0010E": 190, "DP04_0011E": 74, "DP04_0012E": 168, "DP04_0013E": 168, "DP04_0014E": 59, "DP04_0137PE": 6, "DP04_0138PE": 14.5, "DP04_0139PE": 3.4, "DP04_0140PE": 18.4, "DP04_0141PE": 3.6, "DP04_0142PE": 54.1, "NAME": null, "state": 8, "place": 86090}, "acsS0801": {"S0801_C01_001E": 3811, "S0801_C01_002E": 74.6, "S0801_C01_003E": 64.5, "S0801_C01_004E": 10.1, "S0801_C01_005E": 7.6, "S0801_C01_006E": 1.4, "S0801_C01_007E": 1.1, "S0801_C01_008E": 1.08, "S0801_C01_018E": 100, "NAME": null, "state": 8, "place": 86090, "_acsYear": 2024, "_acsSeries": null}, "acsB08301": {"total": 3811, "drive": 2459, "carpool": 385, "transit": 0, "bike": 18, "walk": 17, "other": 73, "work_from_home": 859}, "source": {"acs_profile_endpoint": "https://api.census.gov/data/2024/acs/acs1/profile", "acs_s0801_endpoint": "https://api.census.gov/data/2024/acs/acs5/subject", "acs_b08301_endpoint": "https://api.census.gov/data/2024/acs/acs1"}}