{"fips":"08031","baseYear":2024,"targetYear":2050,"generatedAt":"2026-03-23T05:02:51Z","vintage":2024,"scenarios":{"baseline":[{"year":2024,"totalPopulation":0,"households":0,"unitsNeeded":0},{"year":2025,"totalPopulation":500,"households":190,"unitsNeeded":200},{"year":2026,"totalPopulation":1018,"households":386,"unitsNeeded":406},{"year":2027,"totalPopulation":1554,"households":590,"unitsNeeded":621},{"year":2028,"totalPopulation":2107,"households":801,"unitsNeeded":843},{"year":2029,"totalPopulation":2678,"households":1017,"unitsNeeded":1070},{"year":2030,"totalPopulation":3263,"households":1240,"unitsNeeded":1305},{"year":2031,"totalPopulation":3865,"households":1468,"unitsNeeded":1545},{"year":2032,"totalPopulation":4480,"households":1702,"unitsNeeded":1791},{"year":2033,"totalPopulation":5110,"households":1942,"unitsNeeded":2044},{"year":2034,"totalPopulation":5753,"households":2186,"unitsNeeded":2301},{"year":2035,"totalPopulation":6408,"households":2435,"unitsNeeded":2563},{"year":2036,"totalPopulation":7076,"households":2689,"unitsNeeded":2830},{"year":2037,"totalPopulation":7755,"households":2947,"unitsNeeded":3102},{"year":2038,"totalPopulation":8445,"households":3209,"unitsNeeded":3377},{"year":2039,"totalPopulation":9146,"households":3475,"unitsNeeded":3657},{"year":2040,"totalPopulation":9858,"households":3746,"unitsNeeded":3943},{"year":2041,"totalPopulation":10581,"households":4021,"unitsNeeded":4232},{"year":2042,"totalPopulation":11315,"households":4299,"unitsNeeded":4525},{"year":2043,"totalPopulation":12060,"households":4582,"unitsNeeded":4823},{"year":2044,"totalPopulation":12816,"households":4870,"unitsNeeded":5126},{"year":2045,"totalPopulation":13584,"households":5162,"unitsNeeded":5433},{"year":2046,"totalPopulation":14364,"households":5458,"unitsNeeded":5745},{"year":2047,"totalPopulation":15157,"households":5759,"unitsNeeded":6062},{"year":2048,"totalPopulation":15964,"households":6066,"unitsNeeded":6385},{"year":2049,"totalPopulation":16785,"households":6378,"unitsNeeded":6713},{"year":2050,"totalPopulation":17620,"households":6695,"unitsNeeded":7047}],"low-growth":[{"year":2024,"totalPopulation":0,"households":0,"unitsNeeded":0},{"year":2025,"totalPopulation":250,"households":95,"unitsNeeded":100},{"year":2026,"totalPopulation":503,"households":191,"unitsNeeded":201},{"year":2027,"totalPopulation":758,"households":288,"unitsNeeded":303},{"year":2028,"totalPopulation":1016,"households":386,"unitsNeeded":406},{"year":2029,"totalPopulation":1275,"households":484,"unitsNeeded":509},{"year":2030,"totalPopulation":1536,"households":583,"unitsNeeded":613},{"year":2031,"totalPopulation":1797,"households":682,"unitsNeeded":717},{"year":2032,"totalPopulation":2058,"households":782,"unitsNeeded":823},{"year":2033,"totalPopulation":2320,"households":881,"unitsNeeded":927},{"year":2034,"totalPopulation":2581,"households":981,"unitsNeeded":1032},{"year":2035,"totalPopulation":2842,"households":1079,"unitsNeeded":1135},{"year":2036,"totalPopulation":3101,"households":1178,"unitsNeeded":1240},{"year":2037,"totalPopulation":3359,"households":1276,"unitsNeeded":1343},{"year":2038,"totalPopulation":3616,"households":1374,"unitsNeeded":1446},{"year":2039,"totalPopulation":3871,"households":1471,"unitsNeeded":1548},{"year":2040,"totalPopulation":4125,"households":1567,"unitsNeeded":1649},{"year":2041,"totalPopulation":4376,"households":1663,"unitsNeeded":1750},{"year":2042,"totalPopulation":4626,"households":1758,"unitsNeeded":1850},{"year":2043,"totalPopulation":4874,"households":1852,"unitsNeeded":1949},{"year":2044,"totalPopulation":5120,"households":1945,"unitsNeeded":2047},{"year":2045,"totalPopulation":5365,"households":2038,"unitsNeeded":2145},{"year":2046,"totalPopulation":5608,"households":2131,"unitsNeeded":2243},{"year":2047,"totalPopulation":5849,"households":2222,"unitsNeeded":2338},{"year":2048,"totalPopulation":6090,"households":2314,"unitsNeeded":2435},{"year":2049,"totalPopulation":6328,"households":2404,"unitsNeeded":2530},{"year":2050,"totalPopulation":6566,"households":2495,"unitsNeeded":2626}],"high-growth":[{"year":2024,"totalPopulation":0,"households":0,"unitsNeeded":0},{"year":2025,"totalPopulation":1000,"households":380,"unitsNeeded":400},{"year":2026,"totalPopulation":2045,"households":777,"unitsNeeded":817},{"year":2027,"totalPopulation":3135,"households":1191,"unitsNeeded":1253},{"year":2028,"totalPopulation":4268,"households":1622,"unitsNeeded":1707},{"year":2029,"totalPopulation":5444,"households":2068,"unitsNeeded":2176},{"year":2030,"totalPopulation":6661,"households":2531,"unitsNeeded":2664},{"year":2031,"totalPopulation":7917,"households":3008,"unitsNeeded":3166},{"year":2032,"totalPopulation":9211,"households":3500,"unitsNeeded":3684},{"year":2033,"totalPopulation":10542,"households":4006,"unitsNeeded":4216},{"year":2034,"totalPopulation":11909,"households":4525,"unitsNeeded":4763},{"year":2035,"totalPopulation":13310,"households":5058,"unitsNeeded":5324},{"year":2036,"totalPopulation":14745,"households":5603,"unitsNeeded":5897},{"year":2037,"totalPopulation":16212,"households":6160,"unitsNeeded":6484},{"year":2038,"totalPopulation":17711,"households":6730,"unitsNeeded":7084},{"year":2039,"totalPopulation":19241,"households":7311,"unitsNeeded":7695},{"year":2040,"totalPopulation":20803,"households":7905,"unitsNeeded":8321},{"year":2041,"totalPopulation":22395,"households":8510,"unitsNeeded":8957},{"year":2042,"totalPopulation":24020,"households":9127,"unitsNeeded":9607},{"year":2043,"totalPopulation":25676,"households":9757,"unitsNeeded":10270},{"year":2044,"totalPopulation":27365,"households":10398,"unitsNeeded":10945},{"year":2045,"totalPopulation":29089,"households":11053,"unitsNeeded":11634},{"year":2046,"totalPopulation":30847,"households":11722,"unitsNeeded":12338},{"year":2047,"totalPopulation":32642,"households":12404,"unitsNeeded":13056},{"year":2048,"totalPopulation":34475,"households":13100,"unitsNeeded":13789},{"year":2049,"totalPopulation":36348,"households":13812,"unitsNeeded":14538},{"year":2050,"totalPopulation":38263,"households":14540,"unitsNeeded":15305}]}}