{"updated": "2026-02-27T17:58:48Z", "year": 2022, "countyFips": "08109", "within": 722, "inflow": 725, "outflow": 1174, "source": {"dataset": "LEHD LODES8 OD main (JT00)", "url": "https://lehd.ces.census.gov/data/lodes/LODES8/co/od/co_od_main_JT00_2022.csv.gz"}, "wacYear": 2023, "annualEmployment": {"2019": 1447, "2020": 1338, "2021": 1392, "2022": 1462, "2023": 1498}, "annualWages": {"2019": {"low": 391, "medium": 478, "high": 579}, "2020": {"low": 361, "medium": 442, "high": 535}, "2021": {"low": 376, "medium": 459, "high": 557}, "2022": {"low": 395, "medium": 482, "high": 585}, "2023": {"low": 404, "medium": 494, "high": 599}}, "yoyGrowth": {"2020": -7.53, "2021": 4.04, "2022": 5.03, "2023": 2.46}, "industries": [{"naics": "CNS16", "label": "Healthcare & Social Assistance", "count": 195, "pct": 13.0}, {"naics": "CNS07", "label": "Retail Trade", "count": 165, "pct": 11.0}, {"naics": "CNS18", "label": "Accommodation & Food Services", "count": 150, "pct": 10.0}, {"naics": "CNS12", "label": "Professional & Technical Services", "count": 135, "pct": 9.0}, {"naics": "CNS04", "label": "Construction", "count": 105, "pct": 7.0}, {"naics": "CNS05", "label": "Manufacturing", "count": 90, "pct": 6.0}, {"naics": "CNS14", "label": "Administrative & Waste Services", "count": 90, "pct": 6.0}, {"naics": "CNS20", "label": "Public Administration", "count": 82, "pct": 5.5}, {"naics": "CNS10", "label": "Finance & Insurance", "count": 75, "pct": 5.0}, {"naics": "CNS08", "label": "Transportation & Warehousing", "count": 60, "pct": 4.0}, {"naics": "CNS06", "label": "Wholesale Trade", "count": 60, "pct": 4.0}, {"naics": "CNS19", "label": "Other Services", "count": 52, "pct": 3.5}, {"naics": "CNS15", "label": "Educational Services", "count": 45, "pct": 3.0}, {"naics": "CNS09", "label": "Information", "count": 45, "pct": 3.0}, {"naics": "CNS01", "label": "Agriculture & Mining", "count": 45, "pct": 3.0}, {"naics": "CNS02", "label": "Mining, Quarrying, Oil & Gas", "count": 30, "pct": 2.0}, {"naics": "CNS11", "label": "Real Estate", "count": 30, "pct": 2.0}, {"naics": "CNS17", "label": "Arts & Entertainment", "count": 30, "pct": 2.0}, {"naics": "CNS13", "label": "Management of Companies", "count": 15, "pct": 1.0}, {"naics": "CNS03", "label": "Utilities", "count": 15, "pct": 1.0}]}